Workbook

Sheet Instructions
A1: Expo 2027 Belgrade — Operations Project Plan: Instructions & Legend
A2: This tab explains how the plan is structured and how the Consultant Milestones section should be kept up to date. Read this before editing the plan.
A4: Maintaining the Consultant Milestones Section | J4: Legend: REF Coding Scheme
A5: The Consultant Milestones section tracks all S21 consultant deliverables against the project plan, and must be kept current on a weekly basis so that progress reporting reflects an accurate, real-time picture of delivery. | J5: REF Format | K5: Row Type | L5: Description | O5: Row Colour
A6: Every deliverable and subtask row must carry a date, even where that date is not yet firm. Where a date is tentative, it should still be entered so the schedule remains usable, with a comment added to the cell noting that the date is to be confirmed. This ensures no row is left undated simply because full certainty hasn't been reached. | J6: KM.# | K6: Key Milestone | L6: Top-level programme milestone
A7: Where work has already been completed, it should be added to the plan retrospectively with its actual start and end dates, rather than left blank. The plan is intended to reflect the full history of delivery, not just work that is currently in progress. | J7: CM.DEPT.## | K7: Consultant Milestone (S21) | L7: S21 consultant deliverable, linked to a Key Milestone
A8: Any document produced as part of a deliverable should be referenced in the row, noting that it is stored on the CEG share drive. This keeps the plan as a reliable index of where supporting evidence can be found, without duplicating files across locations. | J8: DEPT-T## | K8: Department Task | L8: Department-owned task
A9: When new work begins under an existing Consultant Milestone, it should be captured as a new sub-line nested beneath that milestone, rather than by editing the milestone row itself. This preserves the milestone as a stable reference point while still allowing the detail beneath it to grow over time. | J9: DEPT-S##.n | K9: Department Subtask | L9: Department-owned subtask, nested under a Task
A10: Finally, by end of day Wednesday each week, every open task must have its status corrected to reflect current progress, with a short written update entered in the "This Week's Update" column. This weekly discipline is what allows the plan to feed directly into the Crowded Event Weekly Report and other leadership reporting without needing to be re-validated each time.
J11: Legend: Status / RAG
A12: Maintaining the Key Milestones Section | J12: Status | L12: Meaning
A13: Key Milestones represent the top-level programme deliverables tracked by the IDR, and this plan needs to stay aligned with that external master so that departmental delivery is always being measured against the milestones that actually matter at programme level. | K13: Complete | L13: Deliverable fully complete
A14: Updates to Key Milestones are currently shared manually to the IDR's master tracker rather than through an automated feed. This means the version held here should be treated as the working copy, with the IDR's master as the single source of truth once an update has been shared — any discrepancy between the two should be resolved in favour of the IDR master. | K14: On Track | L14: Progressing to plan, no material risk
A15: Dates against each Key Milestone should be driven by the department, not set independently within the plan. The date reflects the department's own committed timeline for that deliverable, which keeps ownership and accountability where it belongs and ensures the plan is targeting the right deliverables rather than dates the consultant has assumed on the department's behalf. | K15: At Risk | L15: Risk to schedule/scope — needs attention
K16: Not Started | L16: Work has not yet begun
K17: No Update Received | L17: No SME/department update provided this cycle
A20: Key Milestones
A36: Colour Conventions

Sheet Tracker
A2: Expo 2027 Belgrade — Operations Project Plan | L2: Status Legend: | N2: Complete | O2: Key Milestones
N3: At Risk | O3: SME Milestones (S21)
A4: Project: | C4: Belgrade 2027 | N4: No Update Received | O4: Department Task
A5: Division: | C5: Operations | N5: On Track | O5: Subtasks
A6: Scope: | C6: Operational Departments | N6: Not Started
A7: Last Updated: | C7: 46231
A8: Tier | B8: Type | C8: Sector | D8: Department | E8: Sub-Team | F8: REF | G8: Deliverable | H8: Description of Service | I8: Owner / Support | J8: SME / SME | K8: Start Date | L8: End Date | M8: Status | N8: Comment | O8: Last Reported (Week Ending) | P8: % Complete | Q8: This Week's Update (S21) | R8: Evidence/Link to Docs
A9: 1 | B9: Key Milestone | C9: Operations | D9: Accreditation (ACR) | F9: KM.100 | G9: Event - Time Accreditation System - Go-Live | I9: Department Led | L9: 46296 | M9: At Risk | N9: Why are we printing ET so early? Or this is for bump in passes?
A10: 1 | B10: Key Milestone | C10: Operations | D10: Accreditation (ACR) | F10: KM.110 | G10: Event Time Operations & Programme Closure - Completed | I10: Department Led | L10: 46399 | M10: On Track
A11: 1 | B11: Key Milestone | C11: Operations | D11: Accreditation (ACR) | F11: KM.140 | G11: Accreditation Application Process Commence | I11: Department Led | L11: 46296 | M11: On Track
A12: 1 | B12: Key Milestone | C12: Operations | D12: Accreditation (ACR) | F12: KM.144 | G12: Accreditation Centre Fully Operational | I12: Department Led | L12: 46296 | M12: On Track
A13: 1 | B13: Key Milestone | C13: Operations | D13: Accreditation (ACR) | F13: NEW | G13: Bump In passes Live | I13: Department Led | M13: No Update Received
A14: 1 | B14: Key Milestone | C14: Operations | D14: Accreditation (ACR) | F14: NEW | G14: Event Time Accreditation Stands Up | I14: Department Led | M14: No Update Received
A15: 1 | B15: Key Milestone | C15: Operations | D15: Accreditation (ACR) | F15: NEW | G15: Event Time Accrediation Stands Down | I15: Department Led | M15: No Update Received
A16: 1 | B16: Key Milestone | C16: Operations | D16: Accreditation (ACR) | F16: NEW | G16: Bump Out Passes Live | M16: No Update Received
A17: 1 | B17: Key Milestone | C17: Operations | D17: Accreditation (ACR) | F17: NEW | G17: Zoning Plan & Privilege Matrix Approved | H17: Zoning plan and access privilege matrix signed off. | I17: Department Led | L17: 46266 | M17: Not Started | N17: Proposed new milestone - pending review
A18: 1 | B18: Key Milestone | C18: Operations | D18: Accreditation (ACR) | F18: NEW | G18: Accreditation System & Printers Procured | H18: Accreditation management system and printing hardware procured. | I18: Department Led | L18: 46249 | M18: Not Started | N18: Proposed new milestone - pending review
A19: 1 | B19: Key Milestone | C19: Operations | D19: Accreditation (ACR) | F19: NEW | G19: Accreditation Categories & Types Confirmed | H19: Full set of accreditation types and categories confirmed. | I19: Department Led | L19: 46235 | M19: Not Started | N19: Proposed new milestone - pending review
A20: 2 | B20: SME Milestone | C20: Operations | D20: Accreditation (ACR) | F20: CM.ACR.01 | G20: Support with the establishment of the Accreditation Governance Framework | H20: Establish governance, reporting structures, decision-making processes, RACI and programme assurance approach | I20: SME-Led (S21) | M20: TBC if this is applicable
A21: 2 | B21: SME Milestone | C21: Operations | D21: Accreditation (ACR) | F21: CM.ACR.02 | G21: Accreditation Programme Review & Readiness Assessment | H21: Review strategy, delivery roadmap, milestones, risks, dependencies and operational gaps | I21: SME-Led (S21) | M21: TBC if this is applicable
A22: 2 | B22: SME Milestone | C22: Operations | D22: Accreditation (ACR) | F22: CM.ACR.03 | G22: Accreditation Access Management Framework | H22: Review zoning plans, privilege matrices, access rights, access boards and approval processes | I22: SME-Led (S21) | M22: TBC if this is applicable
A23: 2 | B23: SME Milestone | C23: Operations | D23: Accreditation (ACR) | F23: CM.ACR.04 | G23: Accreditation System Implementation & Readiness | H23: Provide assurance on system procurement, configuration, integration, testing and operational suitability | I23: SME-Led (S21) | M23: TBC if this is applicable
A24: 2 | B24: SME Milestone | C24: Operations | D24: Accreditation (ACR) | F24: CM.ACR.05 | G24: Accreditation Compliance & Data Management Processes | H24: Support GDPR, background checks, data handling, security compliance and governance requirements | I24: SME-Led (S21) | M24: TBC if this is applicable
A25: 2 | B25: SME Milestone | C25: Operations | D25: Accreditation (ACR) | F25: CM.ACR.06 | G25: Accreditation Operational Planning | H25: Review accreditation types, pass design, registration processes, ALO mobilisation and accreditation centre operations | I25: SME-Led (S21) | M25: TBC if this is applicable
A26: 2 | B26: SME Milestone | C26: Operations | D26: Accreditation (ACR) | F26: CM.ACR.07 | G26: Accreditation Operational Readiness Reviews | H26: Assess readiness against agreed criteria, facilitate stakeholder reviews and identify outstanding actions | I26: SME-Led (S21) | M26: TBC if this is applicable
A27: 2 | B27: SME Milestone | C27: Operations | D27: Accreditation (ACR) | F27: CM.ACR.08 | G27: Bump-In/Bump-Out Strategy | H27: Review contractor access strategy, temporary accreditation processes and operational deployment plans | I27: SME-Led (S21) | M27: TBC if this is applicable
A28: 1 | B28: Key Milestone | C28: Operations | D28: C4i | F28: NEW | G28: MOC Space Allocation Finalised | I28: Department Led | M28: No Update Received | N28: I wouldn't use it as a key milestone. Instead space ready for operations and handed over to Space owner.
A29: 1 | B29: Key Milestone | C29: Operations | D29: C4i | F29: NEW | G29: Incident Logging & Reporting Live | I29: Department Led | M29: No Update Received
A30: 1 | B30: Key Milestone | C30: Operations | D30: C4i | F30: NEW | G30: MOC Stands Up | I30: Department Led | L30: 01.May.27 | M30: No Update Received
A31: 1 | B31: Key Milestone | C31: Operations | D31: C4i | F31: NEW | G31: MOC Stands Down | I31: Department Led | M31: No Update Received
A32: 1 | B32: Key Milestone | C32: Operations | D32: C4i | F32: NEW | G32: C4i Framework Approved | H32: Overarching Command, Control, Communications and Information framework signed off. | I32: Department Led | L32: 46266 | M32: Not Started | N32: Proposed new milestone - pending review
A33: 1 | B33: Key Milestone | C33: Operations | D33: C4i | F33: NEW | G33: MOC Operating Model Approved | H33: Main Operations Centre operating model agreed. | I33: Department Led | L33: 46280 | M33: Not Started | N33: Proposed new milestone - pending review
A34: 1 | B34: Key Milestone | C34: Operations | D34: C4i | F34: NEW | G34: Event-Time Governance & Delegations Framework Signed Off | H34: Decision-making authority and delegations for event time agreed. | I34: Department Led | L34: 46296 | M34: Not Started | N34: Proposed new milestone - pending review
A35: 1 | B35: Key Milestone | C35: Operations | D35: C4i | F35: NEW | G35: C4i Communications & Information Management Plan Approved | H35: Plan for communications and information flow across event time agreed. | I35: Department Led | L35: 46310 | M35: Not Started | N35: Proposed new milestone - pending review
A36: 1 | B36: Key Milestone | C36: Operations | D36: C4i | F36: NEW | G36: External Stakeholder Interface Protocols Agreed | H36: Interface protocols with external agencies and stakeholders confirmed. | I36: Department Led | L36: 46327 | M36: Not Started | N36: Proposed new milestone - pending review
A37: 1 | B37: Key Milestone | C37: Operations | D37: C4i | F37: NEW | G37: MOC Readiness Testing Programme Complete | H37: Testing programme for MOC systems and processes complete. | I37: Department Led | L37: 46447 | M37: Not Started | N37: Proposed new milestone - pending review
A38: 1 | B38: Key Milestone | C38: Operations | D38: C4i | F38: NEW | G38: C4i Stakeholder Integration Complete | H38: Integration of departmental desks and functional interfaces within the MOC complete. | I38: Department Led | L38: 46461 | M38: Not Started | N38: Proposed new milestone - pending review
A39: 2 | B39: SME Milestone | C39: Operations | D39: C4i | F39: CM.C4i.01 | G39: C4i Governance & Operating Frameworks | H39: Establish C4i governance, command and control principles, operating model, decision-making structures, reporting processes and operational interfaces. | I39: SME-Led (S21) | J39: Teymur | K39: 46223 | L39: 46295 | M39: On Track
A40: 3 | B40: SME Milestone | C40: Operations | D40: C4i | F40: CM.C4i.01.1 | G40: C4i baseline review and gap analysis complete | H40: Review the C4i Bridging Document V0, Belgrade ConOps, existing MOC design and comparator material against EX27 operational requirements, and issue the gap position. | I40: SME-Led (S21) | J40: Teymur | K40: 46209 | L40: 46234 | M40: Complete | N40: Integrate-first approach: baseline the incumbent position before proposing change.
A41: 3 | B41: SME Milestone | C41: Operations | D41: C4i | F41: CM.C4i.01.2 | G41: C4i Framework V1 produced | H41: Produce the C4i Framework covering purpose, principles, command tiers, operations centre architecture and the severity and escalation model. | I41: SME-Led (S21) | J41: Teymur | K41: 46223 | L41: 46252 | M41: On Track | N41: Anchor date for V1 is 18-Aug-26. Sections 1 to 4 complete at V1; Sections 5 to 9 stubbed pending the structural rulings at CM.C4i.01.2.3.
A42: 4 | B42: SME Milestone | C42: Operations | D42: C4i | F42: CM.C4i.01.2.1 | G42: Framework structure and section architecture agreed | H42: Agree the section skeleton and section owners before drafting content. | I42: SME-Led (S21) | J42: Teymur | K42: 46223 | L42: 46234 | M42: Complete
A43: 4 | B43: SME Milestone | C43: Operations | D43: C4i | F43: CM.C4i.01.2.2 | G43: Sections 1 to 4 drafted (purpose, principles, command tiers, centre architecture) | H43: Draft the framework foundation: C4i definition, operating principles, the four decision tiers and the MOC, EOC and coordination centre architecture. | I43: SME-Led (S21) | J43: Teymur | K43: 46230 | L43: 46248 | M43: On Track
A44: 4 | B44: SME Milestone | C44: Operations | D44: C4i | F44: CM.C4i.01.2.3 | G44: Structural decisions register issued for Project Director ruling | H44: Table the open structural decisions (including the EOC and MOC nesting question) for sign-off, so drafting of the remaining sections is unblocked. | I44: SME-Led (S21) | J44: Teymur | K44: 46238 | L44: 46252 | M44: On Track | N44: Dependant on Security C4i Alignment Meeting
A45: 3 | B45: SME Milestone | C45: Operations | D45: C4i | F45: CM.C4i.01.3 | G45: C4i terminology and naming conventions ratified | H45: Fix a single agreed vocabulary across all C4i documentation: C4i versus C4, EOC as the space and MOC as the function, the CMT naming clash (Crowd Management Team versus Crisis Management Team), and the Bronze, Silver, Gold and Political tier labels. | I45: SME-Led (S21) | J45: Teymur | K45: 46237 | L45: 46265 | M45: On Track
A46: 3 | B46: SME Milestone | C46: Operations | D46: C4i | F46: CM.C4i.01.4 | G46: C4i Framework V1 approved | H46: Framework V1 taken through review and formal approval. | I46: SME-Led (S21) | J46: Teymur | K46: 46252 | L46: 46269 | M46: Not Started | N46: Gate. Unblocks CM.C4i.02.1 C4i Plan V1 drafting.
A47: 3 | B47: SME Milestone | C47: Operations | D47: C4i | F47: CM.C4i.01.5 | G47: C4i Framework V2 completed (Sections 5 to 9) | H47: Complete the remaining framework sections following the structural rulings, and reissue as V2. | I47: SME-Led (S21) | J47: Teymur | K47: 46272 | L47: 46295 | M47: Not Started
A48: 3 | B48: SME Milestone | C48: Operations | D48: C4i | F48: CM.C4i.01.6 | G48: Framework socialisation and departmental briefing complete | H48: Brief departments and consortium partners on the framework, so the model is understood before it is applied through the C4i Plan and SOPs. | I48: SME-Led (S21) | J48: Teymur | K48: 46300 | L48: 46325 | M48: Not Started | N48: Lead with education rather than ownership. Runs alongside the CM.C4i.06.6 alignment cadence.
A49: 2 | B49: SME Milestone | C49: Operations | D49: C4i | F49: CM.C4i.02 | G49: C4i Strategy, Plans & Operational Protocols | H49: Review C4i framework, operational plans, SOPs, guidance documents and protocols to ensure alignment across departments, partners and agencies. | I49: SME-Led (S21) | J49: Teymur | K49: 46266 | L49: 46446 | M49: Not Started | N49: PARENT (Tier 2, fixed). Mirrors C4i-S01.4 and C4i-S01.5. Feeds KM.139 Final C4 Conops Approved, KM.149 All Operating Plans Published (01-Dec-26), KM.143 All Operations Guides Published (01-Oct-26). DATE CHANGE PROPOSED: V1 end of 30-Jan-27 does not cover the SOP suite publication at 28-Feb-27.
A50: 3 | B50: SME Milestone | C50: Operations | D50: C4i | F50: CM.C4i.02.1 | G50: C4i Plan V1 drafted | H50: Full operational detail plan built on the approved framework. | I50: SME-Led (S21) | J50: Teymur | K50: 46266 | L50: 46356 | M50: Not Started | N50: Dependent on CM.C4i.01.4 framework approval. Precedes C4i-S01.4 C4i Plan (Final) Approved (15-Jan-27).
A51: 4 | B51: SME Milestone | C51: Operations | D51: C4i | F51: CM.C4i.02.1.1 | G51: Plan structure and contents agreed with section owners | H51: Agreed skeleton, section owners and contribution deadlines before drafting starts. | I51: SME-Led (S21) | J51: Teymur | K51: 46266 | L51: 46280 | M51: Not Started
A52: 4 | B52: SME Milestone | C52: Operations | D52: C4i | F52: CM.C4i.02.1.2 | G52: Core operating sections drafted | H52: Activation, operating modes, daily rhythm, reporting and interfaces written up. | I52: SME-Led (S21) | J52: Teymur | K52: 46280 | L52: 46326 | M52: Not Started | N52: Draws on CM.C4i.03 operating model outputs.
A53: 4 | B53: SME Milestone | C53: Operations | D53: C4i | F53: CM.C4i.02.1.3 | G53: Annexes and quick-reference cards drafted | H53: Role cards, escalation cards, contact directory and communications annexes. | I53: SME-Led (S21) | J53: Teymur | K53: 46310 | L53: 46356 | M53: Not Started
A54: 3 | B54: SME Milestone | C54: Operations | D54: C4i | F54: CM.C4i.02.2 | G54: Peak and special operating annexes drafted | H54: Named annexes for the periods that break steady state: Opening, National Days, Head of State and VIP visits, Closing, and adverse weather. | I54: SME-Led (S21) | J54: Teymur | K54: 46327 | L54: 46418 | M54: Not Started | N54: Thinking about adding these annexes for specific operational days to streamline site-wide coms. An exposition runs an endurance operation with periodic peaks, not one spike. A single steady-state plan does not cover the peaks, and the peaks are where the model gets tested.
A55: 3 | B55: SME Milestone | C55: Operations | D55: C4i | F55: CM.C4i.02.3 | G55: Degraded and business continuity operating procedures defined | H55: Define how the MOC continues to operate when radio, the incident platform, network, power or the MOC facility itself is lost, including fallback location and manual logging procedure. | I55: SME-Led (S21) | J55: Teymur | K55: 46327 | L55: 46418 | M55: Not Started | N55: NEW. Pairs with CM.C4i.07.3 technology resilience requirements. Distinct from crisis response, which sits outside the C4i model.
A56: 3 | B56: SME Milestone | C56: Operations | D56: C4i | F56: CM.C4i.02.4 | G56: C4i operational protocols and SOP suite defined | H56: Define and draft the SOP set: briefing materials, AM activation, escalation, shift handover, log keeping, SITREP, debrief and stand-down. | I56: SME-Led (S21) | J56: Teymur | K56: 46327 | L56: 46446 | M56: Not Started | N56: Mirrors C4i-S01.5 C4i Operational Protocols & Guidance Documents Published (28-Feb-27). Read across to CM.SEC.09 Security Operating Procedures Review (Matt/Steve).
A57: 4 | B57: SME Milestone | C57: Operations | D57: C4i | F57: CM.C4i.02.4.1 | G57: Core MOC SOPs drafted (activation, handover, log, SITREP, debrief) | H57: The non-negotiable operating procedures for the MOC. | I57: SME-Led (S21) | J57: Teymur | K57: 46346 | L57: 46402 | M57: Not Started
A58: 4 | B58: SME Milestone | C58: Operations | D58: C4i | F58: CM.C4i.02.4.2 | G58: Interface SOPs drafted (EOC, external agency, partner centre) | H58: Procedures governing the seams between centres. | I58: SME-Led (S21) | J58: Teymur | K58: 46392 | L58: 46433 | M58: Not Started | N58: Links C4i-S05.3, VMG-S02.2 and VMG-S02.3.
A59: 4 | B59: SME Milestone | C59: Operations | D59: C4i | F59: CM.C4i.02.4.3 | G59: SOP suite published and referenced in the C4i Plan | H59: Final versions issued to the CEG share drive and cross-referenced from the plan. | I59: SME-Led (S21) | J59: Teymur | K59: 46433 | L59: 46446 | M59: Not Started
A60: 3 | B60: SME Milestone | C60: Operations | D60: C4i | F60: CM.C4i.02.5 | G60: C4i Plan (Final) submitted for approval | H60: Final plan issued for approval and publication. | I60: SME-Led (S21) | J60: Teymur | K60: 46357 | L60: 46412 | M60: Not Started | N60: Mirrors C4i-S01.4 C4i Plan (Final) Approved (15-Jan-27). Also satisfies KM.139 Final C4 Conops Approved and KM.1 CONOPS Approved (15-Jan-27).
A61: 2 | B61: SME Milestone | C61: Operations | D61: C4i | F61: CM.C4i.03 | G61: MOC & EOC Operating Models | H61: Support development of MOC and EOC structures, operating modes, staffing models, seating plans, operating rhythms and coordination centre requirements. | I61: SME-Led (S21) | J61: Teymur | K61: 46223 | L61: 46428 | M61: On Track | N61: PARENT (Tier 2, fixed). Mirrors dept task C4i-T02. Feeds KM MOC Operating Model Approved (15-Sep-26). DATE CHANGE PROPOSED: the master parent end of 15-Sep-26 covers V1 only; C4i-S02.9 Final Operating Model sits at 10-Feb-27.
A62: 3 | B62: SME Milestone | C62: Operations | D62: C4i | F62: CM.C4i.03.1 | G62: MOC operational requirements defined | H62: Define what the MOC must be able to do: functions, occupancy, adjacency, technology and resilience requirements. | I62: SME-Led (S21) | J62: Teymur | K62: 46223 | L62: 46249 | M62: On Track | N62: Mirrors C4i-S02.1 MOC Operational Requirements Defined (15-Aug-26).
A63: 3 | B63: SME Milestone | C63: Operations | D63: C4i | F63: CM.C4i.03.2 | G63: MOC space, layout and seating plan reviewed | H63: Review the existing MOC room layout and fit-out against operational requirements, and advise on seating and space allocation rather than propose a competing layout. | I63: SME-Led (S21) | J63: Teymur | K63: 46249 | L63: 46356 | M63: Not Started | N63: Mirrors C4i-S02.2 MOC Space Design Complete (30-Sep-26) and C4i-S02.5 MOC Departmental Seating & Space Allocation Plan Approved (30-Nov-26). Existing layout and fit-out work is Security-owned, credit explicitly. Links SEC-S02.3.
A64: 3 | B64: SME Milestone | C64: Operations | D64: C4i | F64: CM.C4i.03.3 | G64: MOC FF&E and as-built gap schedule issued | H64: Compare the as-built MOC against the operational requirement and issue a costed gap schedule for furniture, fittings and equipment, with a procurement route for each line. | I64: SME-Led (S21) | J64: Teymur | K64: 46244 | L64: 46295 | M64: Not Started | N64: NEW. Currently the top escalated blocker (FF&E scoping and procurement). Without a costed schedule and a named procurement owner, the seating plan and the operating model both stall.
A65: 3 | B65: SME Milestone | C65: Operations | D65: C4i | F65: CM.C4i.03.4 | G65: MOC Operating Model V1 published | H65: Support production and publication of the V1 MOC operating model. | I65: SME-Led (S21) | J65: Teymur | K65: 46249 | L65: 46295 | M65: Not Started | N65: Mirrors C4i-S02.3 (30-Sep-26). Read across to KM.147 MOC Security Operating Model Approved (SEC, 15-Nov-26). Two operating models must not diverge.
A66: 3 | B66: SME Milestone | C66: Operations | D66: C4i | F66: CM.C4i.03.5 | G66: EOC and departmental coordination centre model V1 | H66: Define the departmental coordination centre tier: which departments run one, what it does and how it reports into the MOC. | I66: SME-Led (S21) | J66: Teymur | K66: 46249 | L66: 46295 | M66: Not Started | N66: Mirrors C4i-S02.4 (30-Sep-26). Overlaps VMG-T02, VMG-S02.3, KM Expo Operations Centre (EOC) Delivered (01-Dec-26) and CM.VMG.T08 (Ilkin). Coordinate with Ilkin to avoid duplicate deliverables. Working position: EOC is the space, MOC is the function within it.
A67: 3 | B67: SME Milestone | C67: Operations | D67: C4i | F67: CM.C4i.03.6 | G67: MOC and EOC representation confirmed (departments, zones, seats) | H67: Close out the placeholder department list and zone count, and confirm which functions are seated, which are on call and which are remote. | I67: SME-Led (S21) | J67: Teymur | K67: 46266 | L67: 46310 | M67: Not Started | N67: NEW. Department list and zone count are currently placeholders in several documents. Seating, fleetmap, staffing and accreditation all depend on one confirmed structure, so this needs to resolve once rather than per document.
A68: 3 | B68: SME Milestone | C68: Operations | D68: C4i | F68: CM.C4i.03.7 | G68: MOC staffing and shift model developed (full operating period) | H68: Develop the staffing model, position list and shift pattern required to run the MOC across pre-opening, the 93 operating days and post-closure. | I68: SME-Led (S21) | J68: Teymur | K68: 46266 | L68: 46376 | M68: Not Started | N68: Mirrors C4i-S02.6 MOC Staffing & Shift Model Approved (20-Dec-26). RENAMED from the V1 wording 93-day shift model: the 93 days cover the core Expo period only (15-May to 15-Aug-27); MOC operations begin before opening and continue after closing. Feeds WKF-S01.1 and WKF-S01.3.
A69: 4 | B69: SME Milestone | C69: Operations | D69: C4i | F69: CM.C4i.03.7.1 | G69: MOC position list and role cards drafted | H69: Every seat in the room defined with a role card. | I69: SME-Led (S21) | J69: Teymur | K69: 46266 | L69: 46310 | M69: Not Started | N69: Feeds WKF-S01.3 position catalogue (titles, JDs, locations, training, accreditation zones).
A70: 4 | B70: SME Milestone | C70: Operations | D70: C4i | F70: CM.C4i.03.7.2 | G70: Shift pattern and rota modelled across the full operating period | H70: Shift lengths, coverage, rest compliance and reliever requirement, modelled separately for ramp-up, steady state and peak days. | I70: SME-Led (S21) | J70: Teymur | K70: 46296 | L70: 46341 | M70: Not Started | N70: Must comply with WKF-S07.27 Shift Duration and Rest Policy and WKF-S07.28.
A71: 4 | B71: SME Milestone | C71: Operations | D71: C4i | F71: CM.C4i.03.7.3 | G71: Fatigue, welfare and rotation model defined for sustained operations | H71: Rotation, leave, reliever depth and fatigue management designed for a multi-month run rather than a short surge. | I71: SME-Led (S21) | J71: Teymur | K71: 46310 | L71: 46356 | M71: Not Started | N71: NEW. The workforce model observed through the MZE series is built for a spike, not a marathon. This is the C4i-side correction for the MOC roster.
... A81: 3 | B81: SME Milestone | C81: Operations | D81: C4i | F81: CM.C4i.04.1 | G81: Delegations of authority and decision thresholds defined | H81: Define who holds which decision, at which command tier, and the financial and operational thresholds attached. | I81: SME-Led (S21) | J81: Teymur | K81: 46266 | L81: 46326 | M81: Not Started | N81: Mirrors C4i-S03.1 (31-Oct-26). Builds on the tier model in CM.C4i.01.2.2. Target: roughly 95 percent of decisions resolving at Bronze.
A82: 4 | B82: SME Milestone | C82: Operations | D82: C4i | F82: CM.C4i.04.1.1 | G82: Decision inventory built | H82: Catalogue of the decisions that actually get made during operations, sourced from the MZE observations and departmental interviews. | I82: SME-Led (S21) | J82: Teymur | K82: 46266 | L82: 46295 | M82: Not Started
A83: 4 | B83: SME Milestone | C83: Operations | D83: C4i | F83: CM.C4i.04.1.2 | G83: Thresholds and delegation levels assigned by tier | H83: Each decision mapped to a tier and a named authority. | I83: SME-Led (S21) | J83: Teymur | K83: 46285 | L83: 46315 | M83: Not Started
A84: 4 | B84: SME Milestone | C84: Operations | D84: C4i | F84: CM.C4i.04.1.3 | G84: Off-hours and degraded-mode delegations defined | H84: Who decides when the primary authority is unavailable. | I84: SME-Led (S21) | J84: Teymur | K84: 46296 | L84: 46326 | M84: Not Started | N84: Links VMG-T01 Define Off-Hours Operating Model.
A85: 3 | B85: SME Milestone | C85: Operations | D85: C4i | F85: CM.C4i.04.2 | G85: Political tier routing defined (Rights Holder and Host State lanes) | H85: Split the Political tier into a rights holder lane (BIE and exposition governance) and a host state lane (Serbian government), each with a named entry point, so escalation routing names which door rather than just saying Political. | I85: SME-Led (S21) | J85: Teymur | K85: 46296 | L85: 46356 | M85: Not Started | N85: NEW. The two lanes hold different authorities and escalate in different directions. Collapsing them creates ambiguous routing during a live incident, which is exactly when it cannot be worked out on the fly.
A86: 3 | B86: SME Milestone | C86: Operations | D86: C4i | F86: CM.C4i.04.3 | G86: Authority matrix and escalation pathways approved | H86: Produce the authority matrix and the escalation routes between Bronze, Silver, Gold and Political. | I86: SME-Led (S21) | J86: Teymur | K86: 46296 | L86: 46356 | M86: Not Started | N86: Mirrors C4i-S03.2 (30-Nov-26). Read across to SEC-S00.3 Roles & Responsibilities Matrix (RACI) and CM.SEC.05 Joint Agency Governance Framework Design, to avoid two competing matrices. No-bypass escalation is the governing principle.
A87: 3 | B87: SME Milestone | C87: Operations | D87: C4i | F87: CM.C4i.04.4 | G87: Issue resolution and risk escalation framework published | H87: Define how issues and risks are raised, triaged, owned and escalated during operations, using the Log, Case, Incident, Issue, Crisis ladder. | I87: SME-Led (S21) | J87: Teymur | K87: 46327 | L87: 46387 | M87: Not Started | N87: Mirrors C4i-S03.3 (31-Dec-26). Reuse the MZE observations and actions tracker structure. Talk-first-then-log applies: talk to the owning function before logging, so logs are not read as complaints.
A88: 3 | B88: SME Milestone | C88: Operations | D88: C4i | F88: CM.C4i.04.5 | G88: Departmental escalation routes mapped and reconciled | H88: Map each department's own escalation route into the C4i model and reconcile the inconsistencies. | I88: SME-Led (S21) | J88: Teymur | K88: 46296 | L88: 46387 | M88: Not Started | N88: Cross-department: GTS-T06, TMO-S02.4, TMO-S05.4, CAW-T07, WKF-S07.7, VOL communication and incident response protocol, VMG-S00.0.8.
A89: 3 | B89: SME Milestone | C89: Operations | D89: C4i | F89: CM.C4i.04.6 | G89: C4i to crisis management interface defined | H89: Define the trigger that moves an event out of the C4i model and into crisis response, who makes that call, how command transfers and how it returns. | I89: SME-Led (S21) | J89: Teymur | K89: 46327 | L89: 46418 | M89: Not Started | N89: NEW. Crisis and emergency response sit outside C4i in a separate procedure, so the seam between the two needs writing down. Also resolves the CMT naming clash in practice. Links CM.CMT.02 Evacuation & Emergency Response Plan Review.
A90: 3 | B90: SME Milestone | C90: Operations | D90: C4i | F90: CM.C4i.04.7 | G90: Scenario-based validation of decision thresholds complete | H90: Test the thresholds and escalation routes against realistic scenarios and refine. | I90: SME-Led (S21) | J90: Teymur | K90: 46402 | L90: 46446 | M90: Not Started | N90: Mirrors C4i-S03.4 (date TBC in dept plan). Delivered through the TTX at CM.C4i.08.4, not as a separate exercise. Also links CM.SEC.07.
A91: 2 | B91: SME Milestone | C91: Operations | D91: C4i | F91: CM.C4i.05 | G91: Communications & Information Management Frameworks | H91: Review communication protocols, radio structures, incident reporting requirements, common operating picture, SITREP processes and information flows. | I91: SME-Led (S21) | J91: Teymur | K91: 46249 | L91: 46433 | M91: Not Started
A92: 3 | B92: SME Milestone | C92: Operations | D92: C4i | F92: CM.C4i.05.1 | G92: Incident logging and reporting requirements issued to IMS supplier | H92: Define and issue the incident logging, categorisation and reporting requirements the incident platform must satisfy. | I92: SME-Led (S21) | J92: Teymur | K92: 46249 | L92: 46295 | M92: On Track | N92: Mirrors C4i-S04.1 (30-Sep-26). Dependency on VMG-T03 and VMG-S03.1. Must land before KM.15 Technology Business Requirements Freeze.
A93: 4 | B93: SME Milestone | C93: Operations | D93: C4i | F93: CM.C4i.05.1.1 | G93: Incident categories and severity scale defined | H93: Categories, severity levels and mandatory data fields, using the Log, Case, Incident, Issue, Crisis ladder. | I93: SME-Led (S21) | J93: Teymur | K93: 46249 | L93: 46275 | M93: On Track
A94: 4 | B94: SME Milestone | C94: Operations | D94: C4i | F94: CM.C4i.05.1.2 | G94: Logging workflow, ownership and audit rules defined | H94: Who logs, who triages, who closes, and the audit requirements. | I94: SME-Led (S21) | J94: Teymur | K94: 46266 | L94: 46290 | M94: Not Started
A95: 4 | B95: SME Milestone | C95: Operations | D95: C4i | F95: CM.C4i.05.1.3 | G95: Requirements pack issued to IMS and Technology | H95: Formal handover of requirements to the platform workstream. | I95: SME-Led (S21) | J95: Teymur | K95: 46285 | L95: 46295 | M95: Not Started | N95: Recipient: VMG-S03.1 and IT. Links VMG-S03.2 Incident Location Identification.
A96: 3 | B96: SME Milestone | C96: Operations | D96: C4i | F96: CM.C4i.05.2 | G96: Common Operating Picture requirements defined | H96: Define what the COP must show, to whom, at what refresh rate and from which source systems. | I96: SME-Led (S21) | J96: Teymur | K96: 46280 | L96: 46326 | M96: Not Started | N96: Mirrors C4i-S04.2 (31-Oct-26). Source systems span VMG (IMS, BMS), TMO-T07, CMT-T06, WKF-T03 and ACR.
A97: 3 | B97: SME Milestone | C97: Operations | D97: C4i | F97: CM.C4i.05.3 | G97: C4i communication protocols defined (internal and external) | H97: Define the communication protocols, channels, conventions and escalation communications between centres, departments and external agencies. | I97: SME-Led (S21) | J97: Teymur | K97: 46296 | L97: 46356 | M97: Not Started | N97: Mirrors C4i-S04.3 (30-Nov-26). Overlaps SEC-S01.6, SEC-S01.5, TMO-S03.4 and VOL comms protocols.
A98: 4 | B98: SME Milestone | C98: Operations | D98: C4i | F98: CM.C4i.05.3.1 | G98: Channel, callsign and voice procedure conventions issued | H98: Naming, callsign structure and voice procedure standards, common across departments. | I98: SME-Led (S21) | J98: Teymur | K98: 46310 | L98: 46356 | M98: Not Started | N98: NEW. Feeds the fleetmap at CM.C4i.05.7 and the training packages at CM.C4i.08.3.
A99: 3 | B99: SME Milestone | C99: Operations | D99: C4i | F99: CM.C4i.05.4 | G99: SITREP templates and reporting cadence approved | H99: Design the situation reporting templates, cut-off times and distribution lists. | I99: SME-Led (S21) | J99: Teymur | K99: 46327 | L99: 46387 | M99: Not Started | N99: Mirrors C4i-S04.4 (31-Dec-26). Must align to CM.C4i.03.10 operating rhythm and VMG-S05.1 Daily Run Sheet.
A100: 3 | B100: SME Milestone | C100: Operations | D100: C4i | F100: CM.C4i.05.5 | G100: MOC to Communications and public information interface agreed | H100: Agree how operational information reaches the communications function, who authorises public statements, and how holding lines are triggered from the MOC. | I100: SME-Led (S21) | J100: Teymur | K100: 46327 | L100: 46418 | M100: Not Started | N100: NEW. Currently no defined route from the operational picture to the public message. This is a predictable failure point at the first incident with a camera on it.
A101: 3 | B101: SME Milestone | C101: Operations | D101: C4i | F101: CM.C4i.05.6 | G101: Information management, records and retention requirements defined | H101: Log retention, evidential standard, data protection and legal hold requirements for MOC records. | I101: SME-Led (S21) | J101: Teymur | K101: 46357 | L101: 46418 | M101: Not Started | N101: NEW. The I in C4i covers the record as well as the flow. Also protects the organisation post-event.
A102: 3 | B102: SME Milestone | C102: Operations | D102: C4i | F102: CM.C4i.05.7 | G102: Org-wide radio fleetmap developed and issued for programming | H102: Build the organisation-wide radio fleetmap and hand it to Technology for programming. | I102: SME-Led (S21) | J102: Teymur | K102: 46249 | L102: 46446 | M102: Not Started | N102: Mirrors C4i-S04.5 (28-Feb-27). Stand-ups with Venue Management already running. VMG fleetmaps (VMG-S05.3) must nest inside the org-wide map, not sit alongside it. FLEETMAP OWNERSHIP STILL UNCONFIRMED, see QA Flags.
A103: 4 | B103: SME Milestone | C103: Operations | D103: C4i | F103: CM.C4i.05.7.1 | G103: Departmental radio requirements collected | H103: Talkgroup, user and coverage requirements gathered per department. | I103: SME-Led (S21) | J103: Teymur | K103: 46249 | L103: 46326 | M103: Not Started
A104: 4 | B104: SME Milestone | C104: Operations | D104: C4i | F104: CM.C4i.05.7.2 | G104: Talkgroup architecture and callsign convention drafted | H104: Fleetmap logical design agreed. | I104: SME-Led (S21) | J104: Teymur | K104: 46296 | L104: 46356 | M104: Not Started
A105: 4 | B105: SME Milestone | C105: Operations | D105: C4i | F105: CM.C4i.05.7.3 | G105: Radio hardware quantity schedule issued | H105: Handset, spare and accessory quantities by department and shift. | I105: SME-Led (S21) | J105: Teymur | K105: 46357 | L105: 46418 | M105: Not Started | N105: Feeds procurement and CM.WKF.07 Workforce Uniform & Equipment Planning.
A106: 4 | B106: SME Milestone | C106: Operations | D106: C4i | F106: CM.C4i.05.7.4 | G106: Fleetmap V1 issued to Technology for programming | H106: Formal issue for programming and spectrum coordination. | I106: SME-Led (S21) | J106: Teymur | K106: 46402 | L106: 46446 | M106: Not Started | N106: Links SEC-S00.8 Wireless Spectrum Activity Plan and KM.12 Technology Design Freeze (15-Mar-27).
A107: 3 | B107: SME Milestone | C107: Operations | D107: C4i | F107: CM.C4i.05.8 | G107: IMS configuration validated against C4i requirements | H107: Validate the delivered platform configuration against the issued C4i requirements and log the gaps. | I107: SME-Led (S21) | J107: Teymur | K107: 46357 | L107: 46446 | M107: Not Started | N107: Mirrors C4i-S04.6 (28-Feb-27). DATE RISK: VMG-S03.5 Test End to End completes 01-May-27, so validation is currently scheduled before its own input. See QA Flags.
A108: 3 | B108: SME Milestone | C108: Operations | D108: C4i | F108: CM.C4i.05.9 | G108: Video wall and COP content plan approved | H108: Agree what is displayed on the MOC video wall, in what layout, sourced from where and maintained by whom. | I108: SME-Led (S21) | J108: Teymur | K108: 46402 | L108: 46477 | M108: Not Started | N108: Mirrors C4i-S04.7 (31-Mar-27). Links VMG-S04.4 and KM.12 Technology Design Freeze.
A109: 2 | B109: SME Milestone | C109: Operations | D109: C4i | F109: CM.C4i.06 | G109: Stakeholder Integration & Interface Management | H109: Establish coordination frameworks, stakeholder maps, RACI models and working arrangements between MOC, EOCs, departments and external agencies. | I109: SME-Led (S21) | J109: Teymur | K109: 46235 | L109: 46446 | M109: No Update Received
A110: 3 | B110: SME Milestone | C110: Operations | D110: C4i | F110: CM.C4i.06.1 | G110: C4i stakeholder map and interface register complete | H110: Build the stakeholder map and the register of every interface the C4i model has to manage. | I110: SME-Led (S21) | J110: Teymur | K110: 46235 | L110: 46265 | M110: On Track
...

Sheet Sheet2
B1: Complete | F1: Key Milestones
B2: At Risk | F2: Consultant Milestones (S21)
B3: No Update Received | F3: Task
B4: On Track | F4: Subtasks
B5: Not Started

Sheet Timeline
A1: EX27 Operations Timeline
A2: Pulled live from Tracker. Formulas update when Tracker changes. | H2: In progress | M2: At risk / blocked | R2: Complete | W2: Workstream summary | AB2: Current week
G4: Sep 2025 | H4: Oct 2025 | L4: Nov 2025 | P4: Dec 2025 | U4: Jan 2026 | Y4: Feb 2026 | AC4: Mar 2026 | AH4: Apr 2026 | AL4: May 2026 | AP4: Jun 2026 | AU4: Jul 2026 | AY4: Aug 2026 | BD4: Sep 2026 | BH4: Oct 2026 | BL4: Nov 2026 | BQ4: Dec 2026 | BU4: Jan 2027 | BY4: Feb 2027 | CC4: Mar 2027 | CH4: Apr 2027 | CL4: May 2027 | CQ4: Jun 2027 | CU4: Jul 2027 | CY4: Aug 2027 | DD4: Sep 2027 | DH4: Oct 2027 | DL4: Nov 2027 | DQ4: Dec 2027
A5: REF | B5: Task Name | C5: Workstream | D5: Owner | E5: Start | F5: Finish | G5: 45929 | H5: 45936 | I5: 45943 | J5: 45950 | K5: 45957 | L5: 45964 | M5: 45971 | N5: 45978 | O5: 45985 | P5: 45992 | Q5: 45999 | R5: 46006 | S5: 46013 | T5: 46020 | U5: 46027 | V5: 46034 | W5: 46041 | X5: 46048 | Y5: 46055 | Z5: 46062 | AA5: 46069 | AB5: 46076 | AC5: 46083 | AD5: 46090 | AE5: 46097 | AF5: 46104 | AG5: 46111 | AH5: 46118 | AI5: 46125 | AJ5: 46132 | AK5: 46139 | AL5: 46146 | AM5: 46153 | AN5: 46160 | AO5: 46167 | AP5: 46174 | AQ5: 46181 | AR5: 46188 | AS5: 46195 | AT5: 46202 | AU5: 46209 | AV5: 46216 | AW5: 46223 | AX5: 46230 | AY5: 46237 | AZ5: 46244 | BA5: 46251 | BB5: 46258 | BC5: 46265 | BD5: 46272 | BE5: 46279 | BF5: 46286 | BG5: 46293 | BH5: 46300 | BI5: 46307 | BJ5: 46314 | BK5: 46321 | BL5: 46328 | BM5: 46335 | BN5: 46342 | BO5: 46349 | BP5: 46356 | BQ5: 46363 | BR5: 46370 | BS5: 46377 | BT5: 46384 | BU5: 46391 | BV5: 46398 | BW5: 46405 | BX5: 46412 | BY5: 46419 | BZ5: 46426 | CA5: 46433 | CB5: 46440 | CC5: 46447 | CD5: 46454 | CE5: 46461 | CF5: 46468 | CG5: 46475 | CH5: 46482 | CI5: 46489 | CJ5: 46496 | CK5: 46503 | CL5: 46510 | CM5: 46517 | CN5: 46524 | CO5: 46531 | CP5: 46538 | CQ5: 46545 | CR5: 46552 | CS5: 46559 | CT5: 46566 | CU5: 46573 | CV5: 46580 | CW5: 46587 | CX5: 46594 | CY5: 46601 | CZ5: 46608 | DA5: 46615 | DB5: 46622 | DC5: 46629 | DD5: 46636 | DE5: 46643 | DF5: 46650 | DG5: 46657 | DH5: 46664 | DI5: 46671 | DJ5: 46678 | DK5: 46685 | DL5: 46692 | DM5: 46699 | DN5: 46706 | DO5: 46713 | DP5: 46720 | DQ5: 46727 | DR5: 46734 | DS5: 46741 | DT5: 46748 | DU5: StatusRef
B6: Accreditation (ACR) | C6: Accreditation (ACR) | E6: =IFERROR(_xlfn.MINIFS(E7:E25,E7:E25,">0"),0) -> 46235 | F6: =IFERROR(_xlfn.MAXIFS(F7:F25,F7:F25,">0"),0) -> 46399 | DU6: WORKSTREAM_SUMMARY
A7: =Tracker!F9 -> KM.100 | B7: =Tracker!G9 -> Event - Time Accreditation System - Go-Live | C7: =TRIM(Tracker!D9) -> Accreditation (ACR) | D7: =IF(TRIM(Tracker!J9)="",Tracker!I9,Tracker!J9) -> Department Led | E7: =IF(ISNUMBER(Tracker!K9),Tracker!K9,IF(ISNUMBER(Tracker!L9),Tracker!L9,0)) -> 46296 | F7: =IF(ISNUMBER(Tracker!L9),Tracker!L9,IF(ISNUMBER(Tracker!K9),Tracker!K9,0)) -> 46296 | DU7: =Tracker!M9 -> At Risk
A8: =Tracker!F10 -> KM.110 | B8: =Tracker!G10 -> Event Time Operations & Programme Closure - Completed | C8: =TRIM(Tracker!D10) -> Accreditation (ACR) | D8: =IF(TRIM(Tracker!J10)="",Tracker!I10,Tracker!J10) -> Department Led | E8: =IF(ISNUMBER(Tracker!K10),Tracker!K10,IF(ISNUMBER(Tracker!L10),Tracker!L10,0)) -> 46399 | F8: =IF(ISNUMBER(Tracker!L10),Tracker!L10,IF(ISNUMBER(Tracker!K10),Tracker!K10,0)) -> 46399 | DU8: =Tracker!M10 -> On Track
A9: =Tracker!F11 -> KM.140 | B9: =Tracker!G11 -> Accreditation Application Process Commence | C9: =TRIM(Tracker!D11) -> Accreditation (ACR) | D9: =IF(TRIM(Tracker!J11)="",Tracker!I11,Tracker!J11) -> Department Led | E9: =IF(ISNUMBER(Tracker!K11),Tracker!K11,IF(ISNUMBER(Tracker!L11),Tracker!L11,0)) -> 46296 | F9: =IF(ISNUMBER(Tracker!L11),Tracker!L11,IF(ISNUMBER(Tracker!K11),Tracker!K11,0)) -> 46296 | DU9: =Tracker!M11 -> On Track
A10: =Tracker!F12 -> KM.144 | B10: =Tracker!G12 -> Accreditation Centre Fully Operational | C10: =TRIM(Tracker!D12) -> Accreditation (ACR) | D10: =IF(TRIM(Tracker!J12)="",Tracker!I12,Tracker!J12) -> Department Led | E10: =IF(ISNUMBER(Tracker!K12),Tracker!K12,IF(ISNUMBER(Tracker!L12),Tracker!L12,0)) -> 46296 | F10: =IF(ISNUMBER(Tracker!L12),Tracker!L12,IF(ISNUMBER(Tracker!K12),Tracker!K12,0)) -> 46296 | DU10: =Tracker!M12 -> On Track
A11: =Tracker!F13 -> NEW | B11: =Tracker!G13 -> Bump In passes Live | C11: =TRIM(Tracker!D13) -> Accreditation (ACR) | D11: =IF(TRIM(Tracker!J13)="",Tracker!I13,Tracker!J13) -> Department Led | E11: =IF(ISNUMBER(Tracker!K13),Tracker!K13,IF(ISNUMBER(Tracker!L13),Tracker!L13,0)) -> 0 | F11: =IF(ISNUMBER(Tracker!L13),Tracker!L13,IF(ISNUMBER(Tracker!K13),Tracker!K13,0)) -> 0 | DU11: =Tracker!M13 -> No Update Received
A12: =Tracker!F14 -> NEW | B12: =Tracker!G14 -> Event Time Accreditation Stands Up | C12: =TRIM(Tracker!D14) -> Accreditation (ACR) | D12: =IF(TRIM(Tracker!J14)="",Tracker!I14,Tracker!J14) -> Department Led | E12: =IF(ISNUMBER(Tracker!K14),Tracker!K14,IF(ISNUMBER(Tracker!L14),Tracker!L14,0)) -> 0 | F12: =IF(ISNUMBER(Tracker!L14),Tracker!L14,IF(ISNUMBER(Tracker!K14),Tracker!K14,0)) -> 0 | DU12: =Tracker!M14 -> No Update Received
A13: =Tracker!F15 -> NEW | B13: =Tracker!G15 -> Event Time Accrediation Stands Down | C13: =TRIM(Tracker!D15) -> Accreditation (ACR) | D13: =IF(TRIM(Tracker!J15)="",Tracker!I15,Tracker!J15) -> Department Led | E13: =IF(ISNUMBER(Tracker!K15),Tracker!K15,IF(ISNUMBER(Tracker!L15),Tracker!L15,0)) -> 0 | F13: =IF(ISNUMBER(Tracker!L15),Tracker!L15,IF(ISNUMBER(Tracker!K15),Tracker!K15,0)) -> 0 | DU13: =Tracker!M15 -> No Update Received
A14: =Tracker!F16 -> NEW | B14: =Tracker!G16 -> Bump Out Passes Live | C14: =TRIM(Tracker!D16) -> Accreditation (ACR) | D14: =IF(TRIM(Tracker!J16)="",Tracker!I16,Tracker!J16) -> 0 | E14: =IF(ISNUMBER(Tracker!K16),Tracker!K16,IF(ISNUMBER(Tracker!L16),Tracker!L16,0)) -> 0 | F14: =IF(ISNUMBER(Tracker!L16),Tracker!L16,IF(ISNUMBER(Tracker!K16),Tracker!K16,0)) -> 0 | DU14: =Tracker!M16 -> No Update Received
A15: =Tracker!F17 -> NEW | B15: =Tracker!G17 -> Zoning Plan & Privilege Matrix Approved | C15: =TRIM(Tracker!D17) -> Accreditation (ACR) | D15: =IF(TRIM(Tracker!J17)="",Tracker!I17,Tracker!J17) -> Department Led | E15: =IF(ISNUMBER(Tracker!K17),Tracker!K17,IF(ISNUMBER(Tracker!L17),Tracker!L17,0)) -> 46266 | F15: =IF(ISNUMBER(Tracker!L17),Tracker!L17,IF(ISNUMBER(Tracker!K17),Tracker!K17,0)) -> 46266 | DU15: =Tracker!M17 -> Not Started
A16: =Tracker!F18 -> NEW | B16: =Tracker!G18 -> Accreditation System & Printers Procured | C16: =TRIM(Tracker!D18) -> Accreditation (ACR) | D16: =IF(TRIM(Tracker!J18)="",Tracker!I18,Tracker!J18) -> Department Led | E16: =IF(ISNUMBER(Tracker!K18),Tracker!K18,IF(ISNUMBER(Tracker!L18),Tracker!L18,0)) -> 46249 | F16: =IF(ISNUMBER(Tracker!L18),Tracker!L18,IF(ISNUMBER(Tracker!K18),Tracker!K18,0)) -> 46249 | DU16: =Tracker!M18 -> Not Started
A17: =Tracker!F19 -> NEW | B17: =Tracker!G19 -> Accreditation Categories & Types Confirmed | C17: =TRIM(Tracker!D19) -> Accreditation (ACR) | D17: =IF(TRIM(Tracker!J19)="",Tracker!I19,Tracker!J19) -> Department Led | E17: =IF(ISNUMBER(Tracker!K19),Tracker!K19,IF(ISNUMBER(Tracker!L19),Tracker!L19,0)) -> 46235 | F17: =IF(ISNUMBER(Tracker!L19),Tracker!L19,IF(ISNUMBER(Tracker!K19),Tracker!K19,0)) -> 46235 | DU17: =Tracker!M19 -> Not Started
A18: =Tracker!F20 -> CM.ACR.01 | B18: =Tracker!G20 -> Support with the establishment of the Accreditation Governance Framework | C18: =TRIM(Tracker!D20) -> Accreditation (ACR) | D18: =IF(TRIM(Tracker!J20)="",Tracker!I20,Tracker!J20) -> SME-Led (S21) | E18: =IF(ISNUMBER(Tracker!K20),Tracker!K20,IF(ISNUMBER(Tracker!L20),Tracker!L20,0)) -> 0 | F18: =IF(ISNUMBER(Tracker!L20),Tracker!L20,IF(ISNUMBER(Tracker!K20),Tracker!K20,0)) -> 0 | DU18: =Tracker!M20 -> TBC if this is applicable
... A25: =Tracker!F27 -> CM.ACR.08 | B25: =Tracker!G27 -> Bump-In/Bump-Out Strategy | C25: =TRIM(Tracker!D27) -> Accreditation (ACR) | D25: =IF(TRIM(Tracker!J27)="",Tracker!I27,Tracker!J27) -> SME-Led (S21) | E25: =IF(ISNUMBER(Tracker!K27),Tracker!K27,IF(ISNUMBER(Tracker!L27),Tracker!L27,0)) -> 0 | F25: =IF(ISNUMBER(Tracker!L27),Tracker!L27,IF(ISNUMBER(Tracker!K27),Tracker!K27,0)) -> 0 | DU25: =Tracker!M27 -> TBC if this is applicable
B26: C4i | C26: C4i | E26: =IFERROR(_xlfn.MINIFS(E27:E150,E27:E150,">0"),0) -> 46209 | F26: =IFERROR(_xlfn.MAXIFS(F27:F150,F27:F150,">0"),0) -> 46508 | DU26: WORKSTREAM_SUMMARY
A27: =Tracker!F28 -> NEW | B27: =Tracker!G28 -> MOC Space Allocation Finalised | C27: =TRIM(Tracker!D28) -> C4i | D27: =IF(TRIM(Tracker!J28)="",Tracker!I28,Tracker!J28) -> Department Led | E27: =IF(ISNUMBER(Tracker!K28),Tracker!K28,IF(ISNUMBER(Tracker!L28),Tracker!L28,0)) -> 0 | F27: =IF(ISNUMBER(Tracker!L28),Tracker!L28,IF(ISNUMBER(Tracker!K28),Tracker!K28,0)) -> 0 | DU27: =Tracker!M28 -> No Update Received
A28: =Tracker!F29 -> NEW | B28: =Tracker!G29 -> Incident Logging & Reporting Live | C28: =TRIM(Tracker!D29) -> C4i | D28: =IF(TRIM(Tracker!J29)="",Tracker!I29,Tracker!J29) -> Department Led | E28: =IF(ISNUMBER(Tracker!K29),Tracker!K29,IF(ISNUMBER(Tracker!L29),Tracker!L29,0)) -> 0 | F28: =IF(ISNUMBER(Tracker!L29),Tracker!L29,IF(ISNUMBER(Tracker!K29),Tracker!K29,0)) -> 0 | DU28: =Tracker!M29 -> No Update Received
A29: =Tracker!F30 -> NEW | B29: =Tracker!G30 -> MOC Stands Up | C29: =TRIM(Tracker!D30) -> C4i | D29: =IF(TRIM(Tracker!J30)="",Tracker!I30,Tracker!J30) -> Department Led | E29: =IF(ISNUMBER(Tracker!K30),Tracker!K30,IF(ISNUMBER(Tracker!L30),Tracker!L30,0)) -> 0 | F29: =IF(ISNUMBER(Tracker!L30),Tracker!L30,IF(ISNUMBER(Tracker!K30),Tracker!K30,0)) -> 0 | DU29: =Tracker!M30 -> No Update Received
A30: =Tracker!F31 -> NEW | B30: =Tracker!G31 -> MOC Stands Down | C30: =TRIM(Tracker!D31) -> C4i | D30: =IF(TRIM(Tracker!J31)="",Tracker!I31,Tracker!J31) -> Department Led | E30: =IF(ISNUMBER(Tracker!K31),Tracker!K31,IF(ISNUMBER(Tracker!L31),Tracker!L31,0)) -> 0 | F30: =IF(ISNUMBER(Tracker!L31),Tracker!L31,IF(ISNUMBER(Tracker!K31),Tracker!K31,0)) -> 0 | DU30: =Tracker!M31 -> No Update Received
A31: =Tracker!F32 -> NEW | B31: =Tracker!G32 -> C4i Framework Approved | C31: =TRIM(Tracker!D32) -> C4i | D31: =IF(TRIM(Tracker!J32)="",Tracker!I32,Tracker!J32) -> Department Led | E31: =IF(ISNUMBER(Tracker!K32),Tracker!K32,IF(ISNUMBER(Tracker!L32),Tracker!L32,0)) -> 46266 | F31: =IF(ISNUMBER(Tracker!L32),Tracker!L32,IF(ISNUMBER(Tracker!K32),Tracker!K32,0)) -> 46266 | DU31: =Tracker!M32 -> Not Started
A32: =Tracker!F33 -> NEW | B32: =Tracker!G33 -> MOC Operating Model Approved | C32: =TRIM(Tracker!D33) -> C4i | D32: =IF(TRIM(Tracker!J33)="",Tracker!I33,Tracker!J33) -> Department Led | E32: =IF(ISNUMBER(Tracker!K33),Tracker!K33,IF(ISNUMBER(Tracker!L33),Tracker!L33,0)) -> 46280 | F32: =IF(ISNUMBER(Tracker!L33),Tracker!L33,IF(ISNUMBER(Tracker!K33),Tracker!K33,0)) -> 46280 | DU32: =Tracker!M33 -> Not Started
A33: =Tracker!F34 -> NEW | B33: =Tracker!G34 -> Event-Time Governance & Delegations Framework Signed Off | C33: =TRIM(Tracker!D34) -> C4i | D33: =IF(TRIM(Tracker!J34)="",Tracker!I34,Tracker!J34) -> Department Led | E33: =IF(ISNUMBER(Tracker!K34),Tracker!K34,IF(ISNUMBER(Tracker!L34),Tracker!L34,0)) -> 46296 | F33: =IF(ISNUMBER(Tracker!L34),Tracker!L34,IF(ISNUMBER(Tracker!K34),Tracker!K34,0)) -> 46296 | DU33: =Tracker!M34 -> Not Started
A34: =Tracker!F35 -> NEW | B34: =Tracker!G35 -> C4i Communications & Information Management Plan Approved | C34: =TRIM(Tracker!D35) -> C4i | D34: =IF(TRIM(Tracker!J35)="",Tracker!I35,Tracker!J35) -> Department Led | E34: =IF(ISNUMBER(Tracker!K35),Tracker!K35,IF(ISNUMBER(Tracker!L35),Tracker!L35,0)) -> 46310 | F34: =IF(ISNUMBER(Tracker!L35),Tracker!L35,IF(ISNUMBER(Tracker!K35),Tracker!K35,0)) -> 46310 | DU34: =Tracker!M35 -> Not Started
A35: =Tracker!F36 -> NEW | B35: =Tracker!G36 -> External Stakeholder Interface Protocols Agreed | C35: =TRIM(Tracker!D36) -> C4i | D35: =IF(TRIM(Tracker!J36)="",Tracker!I36,Tracker!J36) -> Department Led | E35: =IF(ISNUMBER(Tracker!K36),Tracker!K36,IF(ISNUMBER(Tracker!L36),Tracker!L36,0)) -> 46327 | F35: =IF(ISNUMBER(Tracker!L36),Tracker!L36,IF(ISNUMBER(Tracker!K36),Tracker!K36,0)) -> 46327 | DU35: =Tracker!M36 -> Not Started
A36: =Tracker!F37 -> NEW | B36: =Tracker!G37 -> MOC Readiness Testing Programme Complete | C36: =TRIM(Tracker!D37) -> C4i | D36: =IF(TRIM(Tracker!J37)="",Tracker!I37,Tracker!J37) -> Department Led | E36: =IF(ISNUMBER(Tracker!K37),Tracker!K37,IF(ISNUMBER(Tracker!L37),Tracker!L37,0)) -> 46447 | F36: =IF(ISNUMBER(Tracker!L37),Tracker!L37,IF(ISNUMBER(Tracker!K37),Tracker!K37,0)) -> 46447 | DU36: =Tracker!M37 -> Not Started
A37: =Tracker!F38 -> NEW | B37: =Tracker!G38 -> C4i Stakeholder Integration Complete | C37: =TRIM(Tracker!D38) -> C4i | D37: =IF(TRIM(Tracker!J38)="",Tracker!I38,Tracker!J38) -> Department Led | E37: =IF(ISNUMBER(Tracker!K38),Tracker!K38,IF(ISNUMBER(Tracker!L38),Tracker!L38,0)) -> 46461 | F37: =IF(ISNUMBER(Tracker!L38),Tracker!L38,IF(ISNUMBER(Tracker!K38),Tracker!K38,0)) -> 46461 | DU37: =Tracker!M38 -> Not Started
A38: =Tracker!F39 -> CM.C4i.01 | B38: =Tracker!G39 -> C4i Governance & Operating Frameworks | C38: =TRIM(Tracker!D39) -> C4i | D38: =IF(TRIM(Tracker!J39)="",Tracker!I39,Tracker!J39) -> Teymur | E38: =IF(ISNUMBER(Tracker!K39),Tracker!K39,IF(ISNUMBER(Tracker!L39),Tracker!L39,0)) -> 46223 | F38: =IF(ISNUMBER(Tracker!L39),Tracker!L39,IF(ISNUMBER(Tracker!K39),Tracker!K39,0)) -> 46295 | DU38: =Tracker!M39 -> On Track
... A150: =Tracker!F151 -> CM.C4i.10.5 | B150: =Tracker!G151 -> Intellectual Property and document handover process agreed and executed | C150: =TRIM(Tracker!D151) -> C4i | D150: =IF(TRIM(Tracker!J151)="",Tracker!I151,Tracker!J151) -> Teymur | E150: =IF(ISNUMBER(Tracker!K151),Tracker!K151,IF(ISNUMBER(Tracker!L151),Tracker!L151,0)) -> 46266 | F150: =IF(ISNUMBER(Tracker!L151),Tracker!L151,IF(ISNUMBER(Tracker!K151),Tracker!K151,0)) -> 46507 | DU150: =Tracker!M151 -> Not Started
B151: Design & Construction | C151: Design & Construction | E151: =IFERROR(_xlfn.MINIFS(E152:E152,E152:E152,">0"),0) -> 0 | F151: =IFERROR(_xlfn.MAXIFS(F152:F152,F152:F152,">0"),0) -> 0 | DU151: WORKSTREAM_SUMMARY
A152: =Tracker!F152 -> 0 | B152: =Tracker!G152 -> Site Handover Plan | C152: =TRIM(Tracker!D152) -> Design & Construction | D152: =IF(TRIM(Tracker!J152)="",Tracker!I152,Tracker!J152) -> David | E152: =IF(ISNUMBER(Tracker!K152),Tracker!K152,IF(ISNUMBER(Tracker!L152),Tracker!L152,0)) -> 0 | F152: =IF(ISNUMBER(Tracker!L152),Tracker!L152,IF(ISNUMBER(Tracker!K152),Tracker!K152,0)) -> 0 | DU152: =Tracker!M152 -> Complete
B153: Event & Venue Management | C153: Event & Venue Management | E153: =IFERROR(_xlfn.MINIFS(E154:E159,E154:E159,">0"),0) -> 46296 | F153: =IFERROR(_xlfn.MAXIFS(F154:F159,F154:F159,">0"),0) -> 46508 | DU153: WORKSTREAM_SUMMARY
A154: =Tracker!F153 -> KM.116 | B154: =Tracker!G153 -> Final Zone Operating Plan Version Approved | C154: =TRIM(Tracker!D153) -> Event & Venue Management | D154: =IF(TRIM(Tracker!J153)="",Tracker!I153,Tracker!J153) -> Department Led | E154: =IF(ISNUMBER(Tracker!K153),Tracker!K153,IF(ISNUMBER(Tracker!L153),Tracker!L153,0)) -> 46447 | F154: =IF(ISNUMBER(Tracker!L153),Tracker!L153,IF(ISNUMBER(Tracker!K153),Tracker!K153,0)) -> 46447 | DU154: =Tracker!M153 -> No Update Received
A155: =Tracker!F154 -> KM.126 | B155: =Tracker!G154 -> Venue Management On- Site Operations Commence | C155: =TRIM(Tracker!D154) -> Event & Venue Management | D155: =IF(TRIM(Tracker!J154)="",Tracker!I154,Tracker!J154) -> Department Led | E155: =IF(ISNUMBER(Tracker!K154),Tracker!K154,IF(ISNUMBER(Tracker!L154),Tracker!L154,0)) -> 46508 | F155: =IF(ISNUMBER(Tracker!L154),Tracker!L154,IF(ISNUMBER(Tracker!K154),Tracker!K154,0)) -> 46508 | DU155: =Tracker!M154 -> No Update Received
A156: =Tracker!F155 -> KM.137 | B156: =Tracker!G155 -> All Venues Fitness Certificate Approved | C156: =TRIM(Tracker!D155) -> Event & Venue Management | D156: =IF(TRIM(Tracker!J155)="",Tracker!I155,Tracker!J155) -> Department Led | E156: =IF(ISNUMBER(Tracker!K155),Tracker!K155,IF(ISNUMBER(Tracker!L155),Tracker!L155,0)) -> 0 | F156: =IF(ISNUMBER(Tracker!L155),Tracker!L155,IF(ISNUMBER(Tracker!K155),Tracker!K155,0)) -> 0 | DU156: =Tracker!M155 -> No Update Received
A157: =Tracker!F156 -> KM.138 | B157: =Tracker!G156 -> Final All International Participants Operating Plans Approved | C157: =TRIM(Tracker!D156) -> Event & Venue Management | D157: =IF(TRIM(Tracker!J156)="",Tracker!I156,Tracker!J156) -> Department Led | E157: =IF(ISNUMBER(Tracker!K156),Tracker!K156,IF(ISNUMBER(Tracker!L156),Tracker!L156,0)) -> 0 | F157: =IF(ISNUMBER(Tracker!L156),Tracker!L156,IF(ISNUMBER(Tracker!K156),Tracker!K156,0)) -> 0 | DU157: =Tracker!M156 -> No Update Received
A158: =Tracker!F157 -> KM.139 | B158: =Tracker!G157 -> Final C4 Conops Approved | C158: =TRIM(Tracker!D157) -> Event & Venue Management | D158: =IF(TRIM(Tracker!J157)="",Tracker!I157,Tracker!J157) -> Department Led | E158: =IF(ISNUMBER(Tracker!K157),Tracker!K157,IF(ISNUMBER(Tracker!L157),Tracker!L157,0)) -> 0 | F158: =IF(ISNUMBER(Tracker!L157),Tracker!L157,IF(ISNUMBER(Tracker!K157),Tracker!K157,0)) -> 0 | DU158: =Tracker!M157 -> No Update Received
A159: =Tracker!F158 -> KM.143 | B159: =Tracker!G158 -> All Operations Guides Published | C159: =TRIM(Tracker!D158) -> Event & Venue Management | D159: =IF(TRIM(Tracker!J158)="",Tracker!I158,Tracker!J158) -> Department Led | E159: =IF(ISNUMBER(Tracker!K158),Tracker!K158,IF(ISNUMBER(Tracker!L158),Tracker!L158,0)) -> 46296 | F159: =IF(ISNUMBER(Tracker!L158),Tracker!L158,IF(ISNUMBER(Tracker!K158),Tracker!K158,0)) -> 46296 | DU159: =Tracker!M158 -> On Track
B160: EXPO Village Ops | C160: EXPO Village Ops | E160: =IFERROR(_xlfn.MINIFS(E161:E167,E161:E167,">0"),0) -> 46218 | F160: =IFERROR(_xlfn.MAXIFS(F161:F167,F161:F167,">0"),0) -> 46447 | DU160: WORKSTREAM_SUMMARY
A161: =Tracker!F159 -> KM.107 | B161: =Tracker!G159 -> EXPO Village Operator Awarded | C161: =TRIM(Tracker!D159) -> EXPO Village Ops | D161: =IF(TRIM(Tracker!J159)="",Tracker!I159,Tracker!J159) -> Department Led | E161: =IF(ISNUMBER(Tracker!K159),Tracker!K159,IF(ISNUMBER(Tracker!L159),Tracker!L159,0)) -> 46218 | F161: =IF(ISNUMBER(Tracker!L159),Tracker!L159,IF(ISNUMBER(Tracker!K159),Tracker!K159,0)) -> 46218 | DU161: =Tracker!M159 -> At Risk
A162: =Tracker!F160 -> KM.115 | B162: =Tracker!G160 -> Expo Village Fully Operational | C162: =TRIM(Tracker!D160) -> EXPO Village Ops | D162: =IF(TRIM(Tracker!J160)="",Tracker!I160,Tracker!J160) -> Department Led | E162: =IF(ISNUMBER(Tracker!K160),Tracker!K160,IF(ISNUMBER(Tracker!L160),Tracker!L160,0)) -> 46447 | F162: =IF(ISNUMBER(Tracker!L160),Tracker!L160,IF(ISNUMBER(Tracker!K160),Tracker!K160,0)) -> 46447 | DU162: =Tracker!M160 -> On Track
A163: =Tracker!F161 -> KM.141 | B163: =Tracker!G161 -> Partial Expo Village Operations Commence | C163: =TRIM(Tracker!D161) -> EXPO Village Ops | D163: =IF(TRIM(Tracker!J161)="",Tracker!I161,Tracker!J161) -> Department Led | E163: =IF(ISNUMBER(Tracker!K161),Tracker!K161,IF(ISNUMBER(Tracker!L161),Tracker!L161,0)) -> 46296 | F163: =IF(ISNUMBER(Tracker!L161),Tracker!L161,IF(ISNUMBER(Tracker!K161),Tracker!K161,0)) -> 46296 | DU163: =Tracker!M161 -> On Track
A164: =Tracker!F162 -> NEW | B164: =Tracker!G162 -> Technical Certification Complete | C164: =TRIM(Tracker!D162) -> EXPO Village Ops | D164: =IF(TRIM(Tracker!J162)="",Tracker!I162,Tracker!J162) -> Department Led | E164: =IF(ISNUMBER(Tracker!K162),Tracker!K162,IF(ISNUMBER(Tracker!L162),Tracker!L162,0)) -> 0 | F164: =IF(ISNUMBER(Tracker!L162),Tracker!L162,IF(ISNUMBER(Tracker!K162),Tracker!K162,0)) -> 0 | DU164: =Tracker!M162 -> No Update Received
A165: =Tracker!F163 -> NEW | B165: =Tracker!G163 -> Expo Village Apartment Handover | C165: =TRIM(Tracker!D163) -> EXPO Village Ops | D165: =IF(TRIM(Tracker!J163)="",Tracker!I163,Tracker!J163) -> Department Led | E165: =IF(ISNUMBER(Tracker!K163),Tracker!K163,IF(ISNUMBER(Tracker!L163),Tracker!L163,0)) -> 46266 | F165: =IF(ISNUMBER(Tracker!L163),Tracker!L163,IF(ISNUMBER(Tracker!K163),Tracker!K163,0)) -> 46266 | DU165: =Tracker!M163 -> Not Started
A166: =Tracker!F164 -> NEW | B166: =Tracker!G164 -> Expo Village First Guests | C166: =TRIM(Tracker!D164) -> EXPO Village Ops | D166: =IF(TRIM(Tracker!J164)="",Tracker!I164,Tracker!J164) -> Department Led | E166: =IF(ISNUMBER(Tracker!K164),Tracker!K164,IF(ISNUMBER(Tracker!L164),Tracker!L164,0)) -> 46310 | F166: =IF(ISNUMBER(Tracker!L164),Tracker!L164,IF(ISNUMBER(Tracker!K164),Tracker!K164,0)) -> 46310 | DU166: =Tracker!M164 -> Not Started
A167: =Tracker!F165 -> NEW | B167: =Tracker!G165 -> VOC Operational | C167: =TRIM(Tracker!D165) -> EXPO Village Ops | D167: =IF(TRIM(Tracker!J165)="",Tracker!I165,Tracker!J165) -> Department Led | E167: =IF(ISNUMBER(Tracker!K165),Tracker!K165,IF(ISNUMBER(Tracker!L165),Tracker!L165,0)) -> 0 | F167: =IF(ISNUMBER(Tracker!L165),Tracker!L165,IF(ISNUMBER(Tracker!K165),Tracker!K165,0)) -> 0 | DU167: =Tracker!M165 -> 0
B168: Finance | C168: Finance | E168: =IFERROR(_xlfn.MINIFS(E169:E169,E169:E169,">0"),0) -> 46402 | F168: =IFERROR(_xlfn.MAXIFS(F169:F169,F169:F169,">0"),0) -> 46402 | DU168: WORKSTREAM_SUMMARY
A169: =Tracker!F166 -> KM.2 | B169: =Tracker!G166 -> Event-Time Budget Approved | C169: =TRIM(Tracker!D166) -> Finance | D169: =IF(TRIM(Tracker!J166)="",Tracker!I166,Tracker!J166) -> Department Led | E169: =IF(ISNUMBER(Tracker!K166),Tracker!K166,IF(ISNUMBER(Tracker!L166),Tracker!L166,0)) -> 46402 | F169: =IF(ISNUMBER(Tracker!L166),Tracker!L166,IF(ISNUMBER(Tracker!K166),Tracker!K166,0)) -> 46402 | DU169: =Tracker!M166 -> No Update Received
B170: FMT-CAW | C170: FMT-CAW | E170: =IFERROR(_xlfn.MINIFS(E171:E204,E171:E204,">0"),0) -> 45960 | F170: =IFERROR(_xlfn.MAXIFS(F171:F204,F171:F204,">0"),0) -> 46539 | DU170: WORKSTREAM_SUMMARY
A171: =Tracker!F167 -> KM.97 | B171: =Tracker!G167 -> Operations Strategy Approved | C171: =TRIM(Tracker!D167) -> FMT-CAW | D171: =IF(TRIM(Tracker!J167)="",Tracker!I167,Tracker!J167) -> Department Led | E171: =IF(ISNUMBER(Tracker!K167),Tracker!K167,IF(ISNUMBER(Tracker!L167),Tracker!L167,0)) -> 45960 | F171: =IF(ISNUMBER(Tracker!L167),Tracker!L167,IF(ISNUMBER(Tracker!K167),Tracker!K167,0)) -> 45960 | DU171: =Tracker!M167 -> Complete
A172: =Tracker!F168 -> KM.101 | B172: =Tracker!G168 -> Operational Plan Approved | C172: =TRIM(Tracker!D168) -> FMT-CAW | D172: =IF(TRIM(Tracker!J168)="",Tracker!I168,Tracker!J168) -> Department Led | E172: =IF(ISNUMBER(Tracker!K168),Tracker!K168,IF(ISNUMBER(Tracker!L168),Tracker!L168,0)) -> 46054 | F172: =IF(ISNUMBER(Tracker!L168),Tracker!L168,IF(ISNUMBER(Tracker!K168),Tracker!K168,0)) -> 46054 | DU172: =Tracker!M168 -> Complete
A173: =Tracker!F169 -> KM.103 | B173: =Tracker!G169 -> Service Providers Contracted and Started Work | C173: =TRIM(Tracker!D169) -> FMT-CAW | D173: =IF(TRIM(Tracker!J169)="",Tracker!I169,Tracker!J169) -> Department Led | E173: =IF(ISNUMBER(Tracker!K169),Tracker!K169,IF(ISNUMBER(Tracker!L169),Tracker!L169,0)) -> 46266 | F173: =IF(ISNUMBER(Tracker!L169),Tracker!L169,IF(ISNUMBER(Tracker!K169),Tracker!K169,0)) -> 46266 | DU173: =Tracker!M169 -> On Track
A174: =Tracker!F170 -> KM.106 | B174: =Tracker!G170 -> FM Operations On Site Commence | C174: =TRIM(Tracker!D170) -> FMT-CAW | D174: =IF(TRIM(Tracker!J170)="",Tracker!I170,Tracker!J170) -> Department Led | E174: =IF(ISNUMBER(Tracker!K170),Tracker!K170,IF(ISNUMBER(Tracker!L170),Tracker!L170,0)) -> 46204 | F174: =IF(ISNUMBER(Tracker!L170),Tracker!L170,IF(ISNUMBER(Tracker!K170),Tracker!K170,0)) -> 46204 | DU174: =Tracker!M170 -> On Track
A175: =Tracker!F171 -> KM.120 | B175: =Tracker!G171 -> FM Operator Activities Commence | C175: =TRIM(Tracker!D171) -> FMT-CAW | D175: =IF(TRIM(Tracker!J171)="",Tracker!I171,Tracker!J171) -> Department Led | E175: =IF(ISNUMBER(Tracker!K171),Tracker!K171,IF(ISNUMBER(Tracker!L171),Tracker!L171,0)) -> 46478 | F175: =IF(ISNUMBER(Tracker!L171),Tracker!L171,IF(ISNUMBER(Tracker!K171),Tracker!K171,0)) -> 46478 | DU175: =Tracker!M171 -> On Track
A176: =Tracker!F172 -> KM.123 | B176: =Tracker!G172 -> Facilities Management & Cleaning & Waste - Event Testing Phase Complete | C176: =TRIM(Tracker!D172) -> FMT-CAW | D176: =IF(TRIM(Tracker!J172)="",Tracker!I172,Tracker!J172) -> Department Led | E176: =IF(ISNUMBER(Tracker!K172),Tracker!K172,IF(ISNUMBER(Tracker!L172),Tracker!L172,0)) -> 46507 | F176: =IF(ISNUMBER(Tracker!L172),Tracker!L172,IF(ISNUMBER(Tracker!K172),Tracker!K172,0)) -> 46507 | DU176: =Tracker!M172 -> On Track
A177: =Tracker!F173 -> KM.125 | B177: =Tracker!G173 -> Facility Management Operations on Site Commence Fully Operational | C177: =TRIM(Tracker!D173) -> FMT-CAW | D177: =IF(TRIM(Tracker!J173)="",Tracker!I173,Tracker!J173) -> Department Led | E177: =IF(ISNUMBER(Tracker!K173),Tracker!K173,IF(ISNUMBER(Tracker!L173),Tracker!L173,0)) -> 46508 | F177: =IF(ISNUMBER(Tracker!L173),Tracker!L173,IF(ISNUMBER(Tracker!K173),Tracker!K173,0)) -> 46508 | DU177: =Tracker!M173 -> No Update Received
A178: =Tracker!F174 -> NEW | B178: =Tracker!G174 -> Landscaping (Grass, Trees & Shrubs) Installation Complete | C178: =TRIM(Tracker!D174) -> FMT-CAW | D178: =IF(TRIM(Tracker!J174)="",Tracker!I174,Tracker!J174) -> Department Led | E178: =IF(ISNUMBER(Tracker!K174),Tracker!K174,IF(ISNUMBER(Tracker!L174),Tracker!L174,0)) -> 46341 | F178: =IF(ISNUMBER(Tracker!L174),Tracker!L174,IF(ISNUMBER(Tracker!K174),Tracker!K174,0)) -> 46341 | DU178: =Tracker!M174 -> Not Started
A179: =Tracker!F175 -> NEW | B179: =Tracker!G175 -> Technical Maintenance Plan Approved | C179: =TRIM(Tracker!D175) -> FMT-CAW | D179: =IF(TRIM(Tracker!J175)="",Tracker!I175,Tracker!J175) -> Department Led | E179: =IF(ISNUMBER(Tracker!K175),Tracker!K175,IF(ISNUMBER(Tracker!L175),Tracker!L175,0)) -> 46310 | F179: =IF(ISNUMBER(Tracker!L175),Tracker!L175,IF(ISNUMBER(Tracker!K175),Tracker!K175,0)) -> 46310 | DU179: =Tracker!M175 -> Not Started
A180: =Tracker!F176 -> NEW | B180: =Tracker!G176 -> FM Helpdesk Operational | C180: =TRIM(Tracker!D176) -> FMT-CAW | D180: =IF(TRIM(Tracker!J176)="",Tracker!I176,Tracker!J176) -> Department Led | E180: =IF(ISNUMBER(Tracker!K176),Tracker!K176,IF(ISNUMBER(Tracker!L176),Tracker!L176,0)) -> 46357 | F180: =IF(ISNUMBER(Tracker!L176),Tracker!L176,IF(ISNUMBER(Tracker!K176),Tracker!K176,0)) -> 46357 | DU180: =Tracker!M176 -> Not Started
A181: =Tracker!F177 -> NEW | B181: =Tracker!G177 -> Waste & Recycling Partner Contracts Signed | C181: =TRIM(Tracker!D177) -> FMT-CAW | D181: =IF(TRIM(Tracker!J177)="",Tracker!I177,Tracker!J177) -> Department Led | E181: =IF(ISNUMBER(Tracker!K177),Tracker!K177,IF(ISNUMBER(Tracker!L177),Tracker!L177,0)) -> 46295 | F181: =IF(ISNUMBER(Tracker!L177),Tracker!L177,IF(ISNUMBER(Tracker!K177),Tracker!K177,0)) -> 46295 | DU181: =Tracker!M177 -> Not Started
A182: =Tracker!F178 -> NEW | B182: =Tracker!G178 -> Waste Segregation Plan Approved | C182: =TRIM(Tracker!D178) -> FMT-CAW | D182: =IF(TRIM(Tracker!J178)="",Tracker!I178,Tracker!J178) -> Department Led | E182: =IF(ISNUMBER(Tracker!K178),Tracker!K178,IF(ISNUMBER(Tracker!L178),Tracker!L178,0)) -> 46296 | F182: =IF(ISNUMBER(Tracker!L178),Tracker!L178,IF(ISNUMBER(Tracker!K178),Tracker!K178,0)) -> 46296 | DU182: =Tracker!M178 -> Not Started
... A204: =Tracker!F200 -> CM.FMT.07 | B204: =Tracker!G200 -> FM KPI & Reporting Framework Development | C204: =TRIM(Tracker!D200) -> FMT-CAW | D204: =IF(TRIM(Tracker!J200)="",Tracker!I200,Tracker!J200) -> S21 | E204: =IF(ISNUMBER(Tracker!K200),Tracker!K200,IF(ISNUMBER(Tracker!L200),Tracker!L200,0)) -> 0 | F204: =IF(ISNUMBER(Tracker!L200),Tracker!L200,IF(ISNUMBER(Tracker!K200),Tracker!K200,0)) -> 0 | DU204: =Tracker!M200 -> TBC if this is applicable
B205: Guest Services (GTS) | C205: Guest Services (GTS) | E205: =IFERROR(_xlfn.MINIFS(E206:E216,E206:E216,">0"),0) -> 46174 | F205: =IFERROR(_xlfn.MAXIFS(F206:F216,F206:F216,">0"),0) -> 46630 | DU205: WORKSTREAM_SUMMARY
A206: =Tracker!F201 -> KM.98 | B206: =Tracker!G201 -> School Visits Operations Finalised | C206: =TRIM(Tracker!D201) -> Guest Services (GTS) | D206: =IF(TRIM(Tracker!J201)="",Tracker!I201,Tracker!J201) -> Lynn | E206: =IF(ISNUMBER(Tracker!K201),Tracker!K201,IF(ISNUMBER(Tracker!L201),Tracker!L201,0)) -> 46266 | F206: =IF(ISNUMBER(Tracker!L201),Tracker!L201,IF(ISNUMBER(Tracker!K201),Tracker!K201,0)) -> 46357 | DU206: =Tracker!M201 -> On Track
A207: =Tracker!F202 -> KM.109 | B207: =Tracker!G202 -> School Programme Concept of Operations development | C207: =TRIM(Tracker!D202) -> Guest Services (GTS) | D207: =IF(TRIM(Tracker!J202)="",Tracker!I202,Tracker!J202) -> Lynn | E207: =IF(ISNUMBER(Tracker!K202),Tracker!K202,IF(ISNUMBER(Tracker!L202),Tracker!L202,0)) -> 46174 | F207: =IF(ISNUMBER(Tracker!L202),Tracker!L202,IF(ISNUMBER(Tracker!K202),Tracker!K202,0)) -> 46266 | DU207: =Tracker!M202 -> On Track
A208: =Tracker!F203 -> KM.133 | B208: =Tracker!G203 -> School Programme Management System scope defined | C208: =TRIM(Tracker!D203) -> Guest Services (GTS) | D208: =IF(TRIM(Tracker!J203)="",Tracker!I203,Tracker!J203) -> Lynn | E208: =IF(ISNUMBER(Tracker!K203),Tracker!K203,IF(ISNUMBER(Tracker!L203),Tracker!L203,0)) -> 46174 | F208: =IF(ISNUMBER(Tracker!L203),Tracker!L203,IF(ISNUMBER(Tracker!K203),Tracker!K203,0)) -> 46266 | DU208: =Tracker!M203 -> On Track
A209: =Tracker!F204 -> NEW | B209: =Tracker!G204 -> Visitor Complaint Procedure approved | C209: =TRIM(Tracker!D204) -> Guest Services (GTS) | D209: =IF(TRIM(Tracker!J204)="",Tracker!I204,Tracker!J204) -> Lynn | E209: =IF(ISNUMBER(Tracker!K204),Tracker!K204,IF(ISNUMBER(Tracker!L204),Tracker!L204,0)) -> 46216 | F209: =IF(ISNUMBER(Tracker!L204),Tracker!L204,IF(ISNUMBER(Tracker!K204),Tracker!K204,0)) -> 46310 | DU209: =Tracker!M204 -> On Track
A210: =Tracker!F205 -> NEW | B210: =Tracker!G205 -> Contact Centre Operational | C210: =TRIM(Tracker!D205) -> Guest Services (GTS) | D210: =IF(TRIM(Tracker!J205)="",Tracker!I205,Tracker!J205) -> Lynn | E210: =IF(ISNUMBER(Tracker!K205),Tracker!K205,IF(ISNUMBER(Tracker!L205),Tracker!L205,0)) -> 46280 | F210: =IF(ISNUMBER(Tracker!L205),Tracker!L205,IF(ISNUMBER(Tracker!K205),Tracker!K205,0)) -> 46630 | DU210: =Tracker!M205 -> On Track
A211: =Tracker!F206 -> NEW | B211: =Tracker!G206 -> Contact Centre Outsourced Supplier Confirmed | C211: =TRIM(Tracker!D206) -> Guest Services (GTS) | D211: =IF(TRIM(Tracker!J206)="",Tracker!I206,Tracker!J206) -> Lynn | E211: =IF(ISNUMBER(Tracker!K206),Tracker!K206,IF(ISNUMBER(Tracker!L206),Tracker!L206,0)) -> 46249 | F211: =IF(ISNUMBER(Tracker!L206),Tracker!L206,IF(ISNUMBER(Tracker!K206),Tracker!K206,0)) -> 46280 | DU211: =Tracker!M206 -> On Track
A212: =Tracker!F207 -> NEW | B212: =Tracker!G207 -> GTS Department Operating Plan finalised | C212: =TRIM(Tracker!D207) -> Guest Services (GTS) | D212: =IF(TRIM(Tracker!J207)="",Tracker!I207,Tracker!J207) -> Lynn | E212: =IF(ISNUMBER(Tracker!K207),Tracker!K207,IF(ISNUMBER(Tracker!L207),Tracker!L207,0)) -> 46266 | F212: =IF(ISNUMBER(Tracker!L207),Tracker!L207,IF(ISNUMBER(Tracker!K207),Tracker!K207,0)) -> 46266 | DU212: =Tracker!M207 -> On Track
A213: =Tracker!F208 -> NEW | B213: =Tracker!G208 -> Accessibility Equipment Procured | C213: =TRIM(Tracker!D208) -> Guest Services (GTS) | D213: =IF(TRIM(Tracker!J208)="",Tracker!I208,Tracker!J208) -> Lynn | E213: =IF(ISNUMBER(Tracker!K208),Tracker!K208,IF(ISNUMBER(Tracker!L208),Tracker!L208,0)) -> 46371 | F213: =IF(ISNUMBER(Tracker!L208),Tracker!L208,IF(ISNUMBER(Tracker!K208),Tracker!K208,0)) -> 46371 | DU213: =Tracker!M208 -> Not Started
A214: =Tracker!F209 -> NEW | B214: =Tracker!G209 -> School Programme Management System Live | C214: =TRIM(Tracker!D209) -> Guest Services (GTS) | D214: =IF(TRIM(Tracker!J209)="",Tracker!I209,Tracker!J209) -> Lynn | E214: =IF(ISNUMBER(Tracker!K209),Tracker!K209,IF(ISNUMBER(Tracker!L209),Tracker!L209,0)) -> 46266 | F214: =IF(ISNUMBER(Tracker!L209),Tracker!L209,IF(ISNUMBER(Tracker!K209),Tracker!K209,0)) -> 46357 | DU214: =Tracker!M209 -> Not Started
A215: =Tracker!F210 -> NEW | B215: =Tracker!G210 -> GTS Technology & App Support Confirmed | C215: =TRIM(Tracker!D210) -> Guest Services (GTS) | D215: =IF(TRIM(Tracker!J210)="",Tracker!I210,Tracker!J210) -> Lynn | E215: =IF(ISNUMBER(Tracker!K210),Tracker!K210,IF(ISNUMBER(Tracker!L210),Tracker!L210,0)) -> 46388 | F215: =IF(ISNUMBER(Tracker!L210),Tracker!L210,IF(ISNUMBER(Tracker!K210),Tracker!K210,0)) -> 46388 | DU215: =Tracker!M210 -> Not Started
A216: =Tracker!F211 -> NEW | B216: =Tracker!G211 -> GTS Golf Buggy Fleet Operations confirmed | C216: =TRIM(Tracker!D211) -> Guest Services (GTS) | D216: =IF(TRIM(Tracker!J211)="",Tracker!I211,Tracker!J211) -> Lynn | E216: =IF(ISNUMBER(Tracker!K211),Tracker!K211,IF(ISNUMBER(Tracker!L211),Tracker!L211,0)) -> 46447 | F216: =IF(ISNUMBER(Tracker!L211),Tracker!L211,IF(ISNUMBER(Tracker!K211),Tracker!K211,0)) -> 46447 | DU216: =Tracker!M211 -> Not Started
B217: Guest Services (GTS) - Services | C217: Guest Services (GTS) - Services | E217: =IFERROR(_xlfn.MINIFS(E218:E228,E218:E228,">0"),0) -> 46025 | F217: =IFERROR(_xlfn.MAXIFS(F218:F228,F218:F228,">0"),0) -> 46521 | DU217: WORKSTREAM_SUMMARY
A218: =Tracker!F212 -> CM.GTS.01 | B218: =Tracker!G212 -> Guest Services Strategies & Operational Plans | C218: =TRIM(Tracker!D212) -> Guest Services (GTS) - Services | D218: =IF(TRIM(Tracker!J212)="",Tracker!I212,Tracker!J212) -> Lynn | E218: =IF(ISNUMBER(Tracker!K212),Tracker!K212,IF(ISNUMBER(Tracker!L212),Tracker!L212,0)) -> 46280 | F218: =IF(ISNUMBER(Tracker!L212),Tracker!L212,IF(ISNUMBER(Tracker!K212),Tracker!K212,0)) -> 46402 | DU218: =Tracker!M212 -> On Track
A219: =Tracker!F213 -> CM.GTS.01.1 | B219: =Tracker!G213 -> GTS Department Operating Plan finalised | C219: =TRIM(Tracker!D213) -> Guest Services (GTS) - Services | D219: =IF(TRIM(Tracker!J213)="",Tracker!I213,Tracker!J213) -> Lynn | E219: =IF(ISNUMBER(Tracker!K213),Tracker!K213,IF(ISNUMBER(Tracker!L213),Tracker!L213,0)) -> 46204 | F219: =IF(ISNUMBER(Tracker!L213),Tracker!L213,IF(ISNUMBER(Tracker!K213),Tracker!K213,0)) -> 46387 | DU219: =Tracker!M213 -> On Track
A220: =Tracker!F214 -> CM.GTS.02 | B220: =Tracker!G214 -> Contact Centre Operating Plan & Readiness - Phase 1 Launch | C220: =TRIM(Tracker!D214) -> Guest Services (GTS) - Services | D220: =IF(TRIM(Tracker!J214)="",Tracker!I214,Tracker!J214) -> Lynn | E220: =IF(ISNUMBER(Tracker!K214),Tracker!K214,IF(ISNUMBER(Tracker!L214),Tracker!L214,0)) -> 46204 | F220: =IF(ISNUMBER(Tracker!L214),Tracker!L214,IF(ISNUMBER(Tracker!K214),Tracker!K214,0)) -> 46280 | DU220: =Tracker!M214 -> On Track
A221: =Tracker!F215 -> CM.GTS.03 | B221: =Tracker!G215 -> School Programme Operating Plan & Readiness | C221: =TRIM(Tracker!D215) -> Guest Services (GTS) - Services | D221: =IF(TRIM(Tracker!J215)="",Tracker!I215,Tracker!J215) -> Lynn | E221: =IF(ISNUMBER(Tracker!K215),Tracker!K215,IF(ISNUMBER(Tracker!L215),Tracker!L215,0)) -> 46204 | F221: =IF(ISNUMBER(Tracker!L215),Tracker!L215,IF(ISNUMBER(Tracker!K215),Tracker!K215,0)) -> 46521 | DU221: =Tracker!M215 -> On Track
A222: =Tracker!F216 -> CM.GTS.04 | B222: =Tracker!G216 -> Support with the establishment of the Guest Services Workforce & Training Onboarding, Specific Training & any Specialist Training | C222: =TRIM(Tracker!D216) -> Guest Services (GTS) - Services | D222: =IF(TRIM(Tracker!J216)="",Tracker!I216,Tracker!J216) -> Lynn | E222: =IF(ISNUMBER(Tracker!K216),Tracker!K216,IF(ISNUMBER(Tracker!L216),Tracker!L216,0)) -> 46204 | F222: =IF(ISNUMBER(Tracker!L216),Tracker!L216,IF(ISNUMBER(Tracker!K216),Tracker!K216,0)) -> 46327 | DU222: =Tracker!M216 -> Not Started
A223: =Tracker!F217 -> CM.GTS.05 | B223: =Tracker!G217 -> Guest Services Systems & Technology Integration (Chatbot, App, L&F database) | C223: =TRIM(Tracker!D217) -> Guest Services (GTS) - Services | D223: =IF(TRIM(Tracker!J217)="",Tracker!I217,Tracker!J217) -> Lynn | E223: =IF(ISNUMBER(Tracker!K217),Tracker!K217,IF(ISNUMBER(Tracker!L217),Tracker!L217,0)) -> 46204 | F223: =IF(ISNUMBER(Tracker!L217),Tracker!L217,IF(ISNUMBER(Tracker!K217),Tracker!K217,0)) -> 46388 | DU223: =Tracker!M217 -> On Track
A224: =Tracker!F218 -> CM.GTS-S05.1 | B224: =Tracker!G218 -> Specification of the system for schools to register for Expo school visits | C224: =TRIM(Tracker!D218) -> Guest Services (GTS) - Services | D224: =IF(TRIM(Tracker!J218)="",Tracker!I218,Tracker!J218) -> Lynn | E224: =IF(ISNUMBER(Tracker!K218),Tracker!K218,IF(ISNUMBER(Tracker!L218),Tracker!L218,0)) -> 46025 | F224: =IF(ISNUMBER(Tracker!L218),Tracker!L218,IF(ISNUMBER(Tracker!K218),Tracker!K218,0)) -> 46265 | DU224: =Tracker!M218 -> On Track
A225: =Tracker!F219 -> CM.GTS.06 | B225: =Tracker!G219 -> Visitor Journey & Service Standards Confirmation | C225: =TRIM(Tracker!D219) -> Guest Services (GTS) - Services | D225: =IF(TRIM(Tracker!J219)="",Tracker!I219,Tracker!J219) -> Lynn | E225: =IF(ISNUMBER(Tracker!K219),Tracker!K219,IF(ISNUMBER(Tracker!L219),Tracker!L219,0)) -> 46204 | F225: =IF(ISNUMBER(Tracker!L219),Tracker!L219,IF(ISNUMBER(Tracker!K219),Tracker!K219,0)) -> 46388 | DU225: =Tracker!M219 -> Not started
A226: =Tracker!F220 -> CM.GTS.07 | B226: =Tracker!G220 -> Review Guest Services Facilities & Operational Readiness | C226: =TRIM(Tracker!D220) -> Guest Services (GTS) - Services | D226: =IF(TRIM(Tracker!J220)="",Tracker!I220,Tracker!J220) -> Lynn | E226: =IF(ISNUMBER(Tracker!K220),Tracker!K220,IF(ISNUMBER(Tracker!L220),Tracker!L220,0)) -> 46204 | F226: =IF(ISNUMBER(Tracker!L220),Tracker!L220,IF(ISNUMBER(Tracker!K220),Tracker!K220,0)) -> 46521 | DU226: =Tracker!M220 -> On Track
A227: =Tracker!F221 -> CM.GTS.08 | B227: =Tracker!G221 -> Guest Services Readiness Reviews | C227: =TRIM(Tracker!D221) -> Guest Services (GTS) - Services | D227: =IF(TRIM(Tracker!J221)="",Tracker!I221,Tracker!J221) -> Lynn | E227: =IF(ISNUMBER(Tracker!K221),Tracker!K221,IF(ISNUMBER(Tracker!L221),Tracker!L221,0)) -> 46204 | F227: =IF(ISNUMBER(Tracker!L221),Tracker!L221,IF(ISNUMBER(Tracker!K221),Tracker!K221,0)) -> 46491 | DU227: =Tracker!M221 -> On Track
A228: =Tracker!F222 -> CM.GTS.09 | B228: =Tracker!G222 -> Guest Services Paid & Volunteer staff headcount finalisation | C228: =TRIM(Tracker!D222) -> Guest Services (GTS) - Services | D228: =IF(TRIM(Tracker!J222)="",Tracker!I222,Tracker!J222) -> Lynn | E228: =IF(ISNUMBER(Tracker!K222),Tracker!K222,IF(ISNUMBER(Tracker!L222),Tracker!L222,0)) -> 46204 | F228: =IF(ISNUMBER(Tracker!L222),Tracker!L222,IF(ISNUMBER(Tracker!K222),Tracker!K222,0)) -> 46327 | DU228: =Tracker!M222 -> On Track
B229: Health & Safety | C229: Health & Safety | E229: =IFERROR(_xlfn.MINIFS(E230:E230,E230:E230,">0"),0) -> 0 | F229: =IFERROR(_xlfn.MAXIFS(F230:F230,F230:F230,">0"),0) -> 0 | DU229: WORKSTREAM_SUMMARY
A230: =Tracker!F223 -> 0 | B230: =Tracker!G223 -> Site H&S Induction Plan | C230: =TRIM(Tracker!D223) -> Health & Safety | D230: =IF(TRIM(Tracker!J223)="",Tracker!I223,Tracker!J223) -> David | E230: =IF(ISNUMBER(Tracker!K223),Tracker!K223,IF(ISNUMBER(Tracker!L223),Tracker!L223,0)) -> 0 | F230: =IF(ISNUMBER(Tracker!L223),Tracker!L223,IF(ISNUMBER(Tracker!K223),Tracker!K223,0)) -> 0 | DU230: =Tracker!M223 -> Complete
B231: HR | C231: HR | E231: =IFERROR(_xlfn.MINIFS(E232:E233,E232:E233,">0"),0) -> 46357 | F231: =IFERROR(_xlfn.MAXIFS(F232:F233,F232:F233,">0"),0) -> 46402 | DU231: WORKSTREAM_SUMMARY
A232: =Tracker!F224 -> KM.3 | B232: =Tracker!G224 -> Event-Time Headcount Approved | C232: =TRIM(Tracker!D224) -> HR | D232: =IF(TRIM(Tracker!J224)="",Tracker!I224,Tracker!J224) -> Department Led | E232: =IF(ISNUMBER(Tracker!K224),Tracker!K224,IF(ISNUMBER(Tracker!L224),Tracker!L224,0)) -> 46402 | F232: =IF(ISNUMBER(Tracker!L224),Tracker!L224,IF(ISNUMBER(Tracker!K224),Tracker!K224,0)) -> 46402 | DU232: =Tracker!M224 -> No Update Received
A233: =Tracker!F225 -> KM.17 | B233: =Tracker!G225 -> General Training Commence | C233: =TRIM(Tracker!D225) -> HR | D233: =IF(TRIM(Tracker!J225)="",Tracker!I225,Tracker!J225) -> Department Led | E233: =IF(ISNUMBER(Tracker!K225),Tracker!K225,IF(ISNUMBER(Tracker!L225),Tracker!L225,0)) -> 46357 | F233: =IF(ISNUMBER(Tracker!L225),Tracker!L225,IF(ISNUMBER(Tracker!K225),Tracker!K225,0)) -> 46357 | DU233: =Tracker!M225 -> On Track
B234: IT | C234: IT | E234: =IFERROR(_xlfn.MINIFS(E235:E241,E235:E241,">0"),0) -> 46461 | F234: =IFERROR(_xlfn.MAXIFS(F235:F241,F235:F241,">0"),0) -> 46492 | DU234: WORKSTREAM_SUMMARY
A235: =Tracker!F226 -> KM.12 | B235: =Tracker!G226 -> Technology Design Freeze | C235: =TRIM(Tracker!D226) -> IT | D235: =IF(TRIM(Tracker!J226)="",Tracker!I226,Tracker!J226) -> Department Led | E235: =IF(ISNUMBER(Tracker!K226),Tracker!K226,IF(ISNUMBER(Tracker!L226),Tracker!L226,0)) -> 46461 | F235: =IF(ISNUMBER(Tracker!L226),Tracker!L226,IF(ISNUMBER(Tracker!K226),Tracker!K226,0)) -> 46461 | DU235: =Tracker!M226 -> Not Started
A236: =Tracker!F227 -> KM.13 | B236: =Tracker!G227 -> Technology Rehearsal 1 - Complete | C236: =TRIM(Tracker!D227) -> IT | D236: =IF(TRIM(Tracker!J227)="",Tracker!I227,Tracker!J227) -> Department Led | E236: =IF(ISNUMBER(Tracker!K227),Tracker!K227,IF(ISNUMBER(Tracker!L227),Tracker!L227,0)) -> 46487 | F236: =IF(ISNUMBER(Tracker!L227),Tracker!L227,IF(ISNUMBER(Tracker!K227),Tracker!K227,0)) -> 46487 | DU236: =Tracker!M227 -> Not Started
A237: =Tracker!F228 -> KM.14 | B237: =Tracker!G228 -> Technology Rehearsal 2 - Complete | C237: =TRIM(Tracker!D228) -> IT | D237: =IF(TRIM(Tracker!J228)="",Tracker!I228,Tracker!J228) -> Department Led | E237: =IF(ISNUMBER(Tracker!K228),Tracker!K228,IF(ISNUMBER(Tracker!L228),Tracker!L228,0)) -> 46492 | F237: =IF(ISNUMBER(Tracker!L228),Tracker!L228,IF(ISNUMBER(Tracker!K228),Tracker!K228,0)) -> 46492 | DU237: =Tracker!M228 -> Not Started
A238: =Tracker!F229 -> KM.12 | B238: =Tracker!G229 -> Technology Design Freeze | C238: =TRIM(Tracker!D229) -> IT | D238: =IF(TRIM(Tracker!J229)="",Tracker!I229,Tracker!J229) -> Department Led | E238: =IF(ISNUMBER(Tracker!K229),Tracker!K229,IF(ISNUMBER(Tracker!L229),Tracker!L229,0)) -> 0 | F238: =IF(ISNUMBER(Tracker!L229),Tracker!L229,IF(ISNUMBER(Tracker!K229),Tracker!K229,0)) -> 0 | DU238: =Tracker!M229 -> No Update Received
A239: =Tracker!F230 -> KM.13 | B239: =Tracker!G230 -> Technology Rehearsal 1 - Complete | C239: =TRIM(Tracker!D230) -> IT | D239: =IF(TRIM(Tracker!J230)="",Tracker!I230,Tracker!J230) -> Department Led | E239: =IF(ISNUMBER(Tracker!K230),Tracker!K230,IF(ISNUMBER(Tracker!L230),Tracker!L230,0)) -> 0 | F239: =IF(ISNUMBER(Tracker!L230),Tracker!L230,IF(ISNUMBER(Tracker!K230),Tracker!K230,0)) -> 0 | DU239: =Tracker!M230 -> No Update Received
...
